{"class":"GNeuralNet","_ff":{"class":"GIncrementalTransformChainer","before":{"name":"__temp0.csv","attrs":[{"name":"RECRUITED","vals":["Elvish Archer","Elvish Scout","Elvish Fighter","Wose","Elvish Shaman","Merman Hunter","Mage"]},{"name":"enemy faction","vals":["Rebels","Northerners","Loyalists","Drakes","Knalgan Alliance","Undead"]},{"name":"closest enemy to leader","vc":0},{"name":"enemy Bone Shooter","vc":0},{"name":"enemy Bowman","vc":0},{"name":"enemy Cavalryman","vc":0},{"name":"enemy Dark Adept","vc":0},{"name":"enemy Dark Sorcerer","vc":0},{"name":"enemy Deathblade","vc":0},{"name":"enemy Drake Arbiter","vc":0},{"name":"enemy Drake Burner","vc":0},{"name":"enemy Drake Clasher","vc":0},{"name":"enemy Drake Fighter","vc":0},{"name":"enemy Drake Flare","vc":0},{"name":"enemy Drake Glider","vc":0},{"name":"enemy Drake Thrasher","vc":0},{"name":"enemy Drake Warrior","vc":0},{"name":"enemy Dwarvish Fighter","vc":0},{"name":"enemy Dwarvish Guardsman","vc":0},{"name":"enemy Dwarvish Stalwart","vc":0},{"name":"enemy Dwarvish Steelclad","vc":0},{"name":"enemy Dwarvish Thunderer","vc":0},{"name":"enemy Dwarvish Thunderguard","vc":0},{"name":"enemy Dwarvish Ulfserker","vc":0},{"name":"enemy Elder Wose","vc":0},{"name":"enemy Elvish Archer","vc":0},{"name":"enemy Elvish Captain","vc":0},{"name":"enemy Elvish Druid","vc":0},{"name":"enemy Elvish Fighter","vc":0},{"name":"enemy Elvish Hero","vc":0},{"name":"enemy Elvish Marksman","vc":0},{"name":"enemy Elvish Ranger","vc":0},{"name":"enemy Elvish Scout","vc":0},{"name":"enemy Elvish Shaman","vc":0},{"name":"enemy Elvish Sorceress","vc":0},{"name":"enemy Fencer","vc":0},{"name":"enemy Fire Drake","vc":0},{"name":"enemy Footpad","vc":0},{"name":"enemy Ghost","vc":0},{"name":"enemy Ghoul","vc":0},{"name":"enemy Goblin Impaler","vc":0},{"name":"enemy Goblin Spearman","vc":0},{"name":"enemy Gryphon Rider","vc":0},{"name":"enemy Heavy Infantryman","vc":0},{"name":"enemy Horseman","vc":0},{"name":"enemy Javelineer","vc":0},{"name":"enemy Lancer","vc":0},{"name":"enemy Lieutenant","vc":0},{"name":"enemy Longbowman","vc":0},{"name":"enemy Mage","vc":0},{"name":"enemy Merman Fighter","vc":0},{"name":"enemy Merman Hunter","vc":0},{"name":"enemy Merman Netcaster","vc":0},{"name":"enemy Naga Fighter","vc":0},{"name":"enemy Orcish Archer","vc":0},{"name":"enemy Orcish Assassin","vc":0},{"name":"enemy Orcish Crossbowman","vc":0},{"name":"enemy Orcish Grunt","vc":0},{"name":"enemy Orcish Slayer","vc":0},{"name":"enemy Orcish Warrior","vc":0},{"name":"enemy Outlaw","vc":0},{"name":"enemy Pikeman","vc":0},{"name":"enemy Poacher","vc":0},{"name":"enemy Red Mage","vc":0},{"name":"enemy Revenant","vc":0},{"name":"enemy Rogue","vc":0},{"name":"enemy Saurian Augur","vc":0},{"name":"enemy Saurian Oracle","vc":0},{"name":"enemy Saurian Skirmisher","vc":0},{"name":"enemy Saurian Soothsayer","vc":0},{"name":"enemy Shock Trooper","vc":0},{"name":"enemy Skeleton","vc":0},{"name":"enemy Skeleton Archer","vc":0},{"name":"enemy Soulless","vc":0},{"name":"enemy Spearman","vc":0},{"name":"enemy Swordsman","vc":0},{"name":"enemy Tentacle of the Deep","vc":0},{"name":"enemy Thief","vc":0},{"name":"enemy Trapper","vc":0},{"name":"enemy Troll","vc":0},{"name":"enemy Troll Rocklobber","vc":0},{"name":"enemy Troll Whelp","vc":0},{"name":"enemy Vampire Bat","vc":0},{"name":"enemy Walking Corpse","vc":0},{"name":"enemy White Mage","vc":0},{"name":"enemy Wolf Rider","vc":0},{"name":"enemy Wose","vc":0},{"name":"enemy Wraith","vc":0},{"name":"enemy gold","vc":0},{"name":"enemy leader hp pct","vc":0},{"name":"enemy level3+","vc":0},{"name":"enemy total-gold","vc":0},{"name":"enemy unit-gold","vc":0},{"name":"friendly Elder Wose","vc":0},{"name":"friendly Elvish Archer","vc":0},{"name":"friendly Elvish Captain","vc":0},{"name":"friendly Elvish Druid","vc":0},{"name":"friendly Elvish Fighter","vc":0},{"name":"friendly Elvish Hero","vc":0},{"name":"friendly Elvish Marksman","vc":0},{"name":"friendly Elvish Ranger","vc":0},{"name":"friendly Elvish Scout","vc":0},{"name":"friendly Elvish Shaman","vc":0},{"name":"friendly Elvish Sorceress","vc":0},{"name":"friendly Mage","vc":0},{"name":"friendly Merman Hunter","vc":0},{"name":"friendly Merman Netcaster","vc":0},{"name":"friendly Red Mage","vc":0},{"name":"friendly White Mage","vc":0},{"name":"friendly Wose","vc":0},{"name":"friendly gold","vc":0},{"name":"friendly leader hp pct","vc":0},{"name":"friendly total-gold","vc":0},{"name":"friendly unit-gold","vc":0},{"name":"side","vc":0},{"name":"terrain-forest","vc":0},{"name":"terrain-map-size","vc":0},{"name":"terrain-mountain-hill","vc":0},{"name":"terrain-water-swamp","vc":0},{"name":"time of day","vc":0},{"name":"total-gold-ratio","vc":0},{"name":"turn","vc":0},{"name":"village-control-margin","vc":0},{"name":"village-control-ratio","vc":0},{"name":"village-enemy","vc":0},{"name":"village-friendly","vc":0},{"name":"village-neutral","vc":0},{"name":"enemy Blood Bat","vc":0},{"name":"enemy Dragoon","vc":0},{"name":"enemy Elvish Rider","vc":0},{"name":"enemy Goblin Rouser","vc":0},{"name":"enemy Gryphon Master","vc":0},{"name":"enemy Knight","vc":0},{"name":"enemy Merman Spearman","vc":0},{"name":"enemy Merman Warrior","vc":0},{"name":"enemy Naga Warrior","vc":0},{"name":"enemy Saurian Ambusher","vc":0},{"name":"enemy Shadow","vc":0},{"name":"enemy Sky Drake","vc":0},{"name":"friendly Elvish Rider","vc":0},{"name":"friendly Merman Spearman","vc":0},{"name":"enemy Goblin Pillager","vc":0},{"name":"enemy Goblin Knight","vc":0},{"name":"enemy Necrophage","vc":0},{"name":"enemy Dwarvish Berserker","vc":0}]},"after":{"name":"Untitled","attrs":[{"name":"RECRUITED_'Elvish Archer'","vc":0},{"name":"RECRUITED_'Elvish Archer''Elvish Scout'","vc":0},{"name":"RECRUITED_'Elvish Archer''Elvish Scout''Elvish Fighter'","vc":0},{"name":"RECRUITED_'Elvish Archer''Elvish Scout''Elvish Fighter'Wose","vc":0},{"name":"RECRUITED_'Elvish Archer''Elvish Scout''Elvish Fighter'Wose'Elvish Shaman'","vc":0},{"name":"RECRUITED_'Elvish Archer''Elvish Scout''Elvish Fighter'Wose'Elvish Shaman''Merman Hunter'","vc":0},{"name":"RECRUITED_'Elvish Archer''Elvish Scout''Elvish Fighter'Wose'Elvish Shaman''Merman Hunter'Mage","vc":0},{"name":"enemy faction_Rebels","vc":0},{"name":"enemy faction_RebelsNortherners","vc":0},{"name":"enemy faction_RebelsNorthernersLoyalists","vc":0},{"name":"enemy faction_RebelsNorthernersLoyalistsDrakes","vc":0},{"name":"enemy faction_RebelsNorthernersLoyalistsDrakes'Knalgan Alliance'","vc":0},{"name":"enemy faction_RebelsNorthernersLoyalistsDrakes'Knalgan Alliance'Undead","vc":0},{"name":"closest enemy to leader","vc":0},{"name":"enemy Bone Shooter","vc":0},{"name":"enemy Bowman","vc":0},{"name":"enemy Cavalryman","vc":0},{"name":"enemy Dark Adept","vc":0},{"name":"enemy Dark Sorcerer","vc":0},{"name":"enemy Deathblade","vc":0},{"name":"enemy Drake Arbiter","vc":0},{"name":"enemy Drake Burner","vc":0},{"name":"enemy Drake Clasher","vc":0},{"name":"enemy Drake Fighter","vc":0},{"name":"enemy Drake Flare","vc":0},{"name":"enemy Drake Glider","vc":0},{"name":"enemy Drake Thrasher","vc":0},{"name":"enemy Drake Warrior","vc":0},{"name":"enemy Dwarvish Fighter","vc":0},{"name":"enemy Dwarvish Guardsman","vc":0},{"name":"enemy Dwarvish Stalwart","vc":0},{"name":"enemy Dwarvish Steelclad","vc":0},{"name":"enemy Dwarvish Thunderer","vc":0},{"name":"enemy Dwarvish Thunderguard","vc":0},{"name":"enemy Dwarvish Ulfserker","vc":0},{"name":"enemy Elder Wose","vc":0},{"name":"enemy Elvish Archer","vc":0},{"name":"enemy Elvish Captain","vc":0},{"name":"enemy Elvish Druid","vc":0},{"name":"enemy Elvish Fighter","vc":0},{"name":"enemy Elvish Hero","vc":0},{"name":"enemy Elvish Marksman","vc":0},{"name":"enemy Elvish Ranger","vc":0},{"name":"enemy Elvish Scout","vc":0},{"name":"enemy Elvish Shaman","vc":0},{"name":"enemy Elvish Sorceress","vc":0},{"name":"enemy Fencer","vc":0},{"name":"enemy Fire Drake","vc":0},{"name":"enemy Footpad","vc":0},{"name":"enemy Ghost","vc":0},{"name":"enemy Ghoul","vc":0},{"name":"enemy Goblin Impaler","vc":0},{"name":"enemy Goblin Spearman","vc":0},{"name":"enemy Gryphon Rider","vc":0},{"name":"enemy Heavy Infantryman","vc":0},{"name":"enemy Horseman","vc":0},{"name":"enemy Javelineer","vc":0},{"name":"enemy Lancer","vc":0},{"name":"enemy Lieutenant","vc":0},{"name":"enemy Longbowman","vc":0},{"name":"enemy Mage","vc":0},{"name":"enemy Merman Fighter","vc":0},{"name":"enemy Merman Hunter","vc":0},{"name":"enemy Merman Netcaster","vc":0},{"name":"enemy Naga Fighter","vc":0},{"name":"enemy Orcish Archer","vc":0},{"name":"enemy Orcish Assassin","vc":0},{"name":"enemy Orcish Crossbowman","vc":0},{"name":"enemy Orcish Grunt","vc":0},{"name":"enemy Orcish Slayer","vc":0},{"name":"enemy Orcish Warrior","vc":0},{"name":"enemy Outlaw","vc":0},{"name":"enemy Pikeman","vc":0},{"name":"enemy Poacher","vc":0},{"name":"enemy Red Mage","vc":0},{"name":"enemy Revenant","vc":0},{"name":"enemy Rogue","vc":0},{"name":"enemy Saurian Augur","vc":0},{"name":"enemy Saurian Oracle","vc":0},{"name":"enemy Saurian Skirmisher","vc":0},{"name":"enemy Saurian Soothsayer","vc":0},{"name":"enemy Shock Trooper","vc":0},{"name":"enemy Skeleton","vc":0},{"name":"enemy Skeleton Archer","vc":0},{"name":"enemy Soulless","vc":0},{"name":"enemy Spearman","vc":0},{"name":"enemy Swordsman","vc":0},{"name":"enemy Tentacle of the Deep","vc":0},{"name":"enemy Thief","vc":0},{"name":"enemy Trapper","vc":0},{"name":"enemy Troll","vc":0},{"name":"enemy Troll Rocklobber","vc":0},{"name":"enemy Troll Whelp","vc":0},{"name":"enemy Vampire Bat","vc":0},{"name":"enemy Walking Corpse","vc":0},{"name":"enemy White Mage","vc":0},{"name":"enemy Wolf Rider","vc":0},{"name":"enemy Wose","vc":0},{"name":"enemy Wraith","vc":0},{"name":"enemy gold","vc":0},{"name":"enemy leader hp pct","vc":0},{"name":"enemy level3+","vc":0},{"name":"enemy total-gold","vc":0},{"name":"enemy unit-gold","vc":0},{"name":"friendly Elder Wose","vc":0},{"name":"friendly Elvish Archer","vc":0},{"name":"friendly Elvish Captain","vc":0},{"name":"friendly Elvish Druid","vc":0},{"name":"friendly Elvish Fighter","vc":0},{"name":"friendly Elvish Hero","vc":0},{"name":"friendly Elvish Marksman","vc":0},{"name":"friendly Elvish Ranger","vc":0},{"name":"friendly Elvish Scout","vc":0},{"name":"friendly Elvish Shaman","vc":0},{"name":"friendly Elvish Sorceress","vc":0},{"name":"friendly Mage","vc":0},{"name":"friendly Merman Hunter","vc":0},{"name":"friendly Merman Netcaster","vc":0},{"name":"friendly Red Mage","vc":0},{"name":"friendly White Mage","vc":0},{"name":"friendly Wose","vc":0},{"name":"friendly gold","vc":0},{"name":"friendly leader hp pct","vc":0},{"name":"friendly total-gold","vc":0},{"name":"friendly unit-gold","vc":0},{"name":"side","vc":0},{"name":"terrain-forest","vc":0},{"name":"terrain-map-size","vc":0},{"name":"terrain-mountain-hill","vc":0},{"name":"terrain-water-swamp","vc":0},{"name":"time of day","vc":0},{"name":"total-gold-ratio","vc":0},{"name":"turn","vc":0},{"name":"village-control-margin","vc":0},{"name":"village-control-ratio","vc":0},{"name":"village-enemy","vc":0},{"name":"village-friendly","vc":0},{"name":"village-neutral","vc":0},{"name":"enemy Blood Bat","vc":0},{"name":"enemy Dragoon","vc":0},{"name":"enemy Elvish Rider","vc":0},{"name":"enemy Goblin Rouser","vc":0},{"name":"enemy Gryphon Master","vc":0},{"name":"enemy Knight","vc":0},{"name":"enemy Merman Spearman","vc":0},{"name":"enemy Merman Warrior","vc":0},{"name":"enemy Naga Warrior","vc":0},{"name":"enemy Saurian Ambusher","vc":0},{"name":"enemy Shadow","vc":0},{"name":"enemy Sky Drake","vc":0},{"name":"friendly Elvish Rider","vc":0},{"name":"friendly Merman Spearman","vc":0},{"name":"enemy Goblin Pillager","vc":0},{"name":"enemy Goblin Knight","vc":0},{"name":"enemy Necrophage","vc":0},{"name":"enemy Dwarvish Berserker","vc":0}]},"first":{"class":"GNominalToCat","before":{"name":"__temp0.csv","attrs":[{"name":"RECRUITED","vals":["Elvish Archer","Elvish Scout","Elvish Fighter","Wose","Elvish Shaman","Merman Hunter","Mage"]},{"name":"enemy faction","vals":["Rebels","Northerners","Loyalists","Drakes","Knalgan Alliance","Undead"]},{"name":"closest enemy to leader","vc":0},{"name":"enemy Bone Shooter","vc":0},{"name":"enemy Bowman","vc":0},{"name":"enemy Cavalryman","vc":0},{"name":"enemy Dark Adept","vc":0},{"name":"enemy Dark Sorcerer","vc":0},{"name":"enemy Deathblade","vc":0},{"name":"enemy Drake Arbiter","vc":0},{"name":"enemy Drake Burner","vc":0},{"name":"enemy Drake Clasher","vc":0},{"name":"enemy Drake Fighter","vc":0},{"name":"enemy Drake Flare","vc":0},{"name":"enemy Drake Glider","vc":0},{"name":"enemy Drake Thrasher","vc":0},{"name":"enemy Drake Warrior","vc":0},{"name":"enemy Dwarvish Fighter","vc":0},{"name":"enemy Dwarvish Guardsman","vc":0},{"name":"enemy Dwarvish Stalwart","vc":0},{"name":"enemy Dwarvish Steelclad","vc":0},{"name":"enemy Dwarvish Thunderer","vc":0},{"name":"enemy Dwarvish Thunderguard","vc":0},{"name":"enemy Dwarvish Ulfserker","vc":0},{"name":"enemy Elder Wose","vc":0},{"name":"enemy Elvish Archer","vc":0},{"name":"enemy Elvish Captain","vc":0},{"name":"enemy Elvish Druid","vc":0},{"name":"enemy Elvish Fighter","vc":0},{"name":"enemy Elvish Hero","vc":0},{"name":"enemy Elvish Marksman","vc":0},{"name":"enemy Elvish Ranger","vc":0},{"name":"enemy Elvish Scout","vc":0},{"name":"enemy Elvish Shaman","vc":0},{"name":"enemy Elvish Sorceress","vc":0},{"name":"enemy Fencer","vc":0},{"name":"enemy Fire Drake","vc":0},{"name":"enemy Footpad","vc":0},{"name":"enemy Ghost","vc":0},{"name":"enemy Ghoul","vc":0},{"name":"enemy Goblin Impaler","vc":0},{"name":"enemy Goblin Spearman","vc":0},{"name":"enemy Gryphon Rider","vc":0},{"name":"enemy Heavy Infantryman","vc":0},{"name":"enemy Horseman","vc":0},{"name":"enemy Javelineer","vc":0},{"name":"enemy Lancer","vc":0},{"name":"enemy Lieutenant","vc":0},{"name":"enemy Longbowman","vc":0},{"name":"enemy Mage","vc":0},{"name":"enemy Merman Fighter","vc":0},{"name":"enemy Merman Hunter","vc":0},{"name":"enemy Merman Netcaster","vc":0},{"name":"enemy Naga Fighter","vc":0},{"name":"enemy Orcish Archer","vc":0},{"name":"enemy Orcish Assassin","vc":0},{"name":"enemy Orcish Crossbowman","vc":0},{"name":"enemy Orcish Grunt","vc":0},{"name":"enemy Orcish Slayer","vc":0},{"name":"enemy Orcish Warrior","vc":0},{"name":"enemy Outlaw","vc":0},{"name":"enemy Pikeman","vc":0},{"name":"enemy Poacher","vc":0},{"name":"enemy Red Mage","vc":0},{"name":"enemy Revenant","vc":0},{"name":"enemy Rogue","vc":0},{"name":"enemy Saurian Augur","vc":0},{"name":"enemy Saurian Oracle","vc":0},{"name":"enemy Saurian Skirmisher","vc":0},{"name":"enemy Saurian Soothsayer","vc":0},{"name":"enemy Shock Trooper","vc":0},{"name":"enemy Skeleton","vc":0},{"name":"enemy Skeleton Archer","vc":0},{"name":"enemy Soulless","vc":0},{"name":"enemy Spearman","vc":0},{"name":"enemy Swordsman","vc":0},{"name":"enemy Tentacle of the Deep","vc":0},{"name":"enemy Thief","vc":0},{"name":"enemy Trapper","vc":0},{"name":"enemy Troll","vc":0},{"name":"enemy Troll Rocklobber","vc":0},{"name":"enemy Troll Whelp","vc":0},{"name":"enemy Vampire Bat","vc":0},{"name":"enemy Walking Corpse","vc":0},{"name":"enemy White Mage","vc":0},{"name":"enemy Wolf Rider","vc":0},{"name":"enemy Wose","vc":0},{"name":"enemy Wraith","vc":0},{"name":"enemy gold","vc":0},{"name":"enemy leader hp pct","vc":0},{"name":"enemy level3+","vc":0},{"name":"enemy total-gold","vc":0},{"name":"enemy unit-gold","vc":0},{"name":"friendly Elder Wose","vc":0},{"name":"friendly Elvish Archer","vc":0},{"name":"friendly Elvish Captain","vc":0},{"name":"friendly Elvish Druid","vc":0},{"name":"friendly Elvish Fighter","vc":0},{"name":"friendly Elvish Hero","vc":0},{"name":"friendly Elvish Marksman","vc":0},{"name":"friendly Elvish Ranger","vc":0},{"name":"friendly Elvish Scout","vc":0},{"name":"friendly Elvish Shaman","vc":0},{"name":"friendly Elvish Sorceress","vc":0},{"name":"friendly Mage","vc":0},{"name":"friendly Merman Hunter","vc":0},{"name":"friendly Merman Netcaster","vc":0},{"name":"friendly Red Mage","vc":0},{"name":"friendly White Mage","vc":0},{"name":"friendly Wose","vc":0},{"name":"friendly gold","vc":0},{"name":"friendly leader hp pct","vc":0},{"name":"friendly total-gold","vc":0},{"name":"friendly unit-gold","vc":0},{"name":"side","vc":0},{"name":"terrain-forest","vc":0},{"name":"terrain-map-size","vc":0},{"name":"terrain-mountain-hill","vc":0},{"name":"terrain-water-swamp","vc":0},{"name":"time of day","vc":0},{"name":"total-gold-ratio","vc":0},{"name":"turn","vc":0},{"name":"village-control-margin","vc":0},{"name":"village-control-ratio","vc":0},{"name":"village-enemy","vc":0},{"name":"village-friendly","vc":0},{"name":"village-neutral","vc":0},{"name":"enemy Blood Bat","vc":0},{"name":"enemy Dragoon","vc":0},{"name":"enemy Elvish Rider","vc":0},{"name":"enemy Goblin Rouser","vc":0},{"name":"enemy Gryphon Master","vc":0},{"name":"enemy Knight","vc":0},{"name":"enemy Merman Spearman","vc":0},{"name":"enemy Merman Warrior","vc":0},{"name":"enemy Naga Warrior","vc":0},{"name":"enemy Saurian Ambusher","vc":0},{"name":"enemy Shadow","vc":0},{"name":"enemy Sky Drake","vc":0},{"name":"friendly Elvish Rider","vc":0},{"name":"friendly Merman Spearman","vc":0},{"name":"enemy Goblin Pillager","vc":0},{"name":"enemy Goblin Knight","vc":0},{"name":"enemy Necrophage","vc":0},{"name":"enemy Dwarvish Berserker","vc":0}]},"after":{"name":"Untitled","attrs":[{"name":"RECRUITED_'Elvish Archer'","vc":0},{"name":"RECRUITED_'Elvish Archer''Elvish Scout'","vc":0},{"name":"RECRUITED_'Elvish Archer''Elvish Scout''Elvish Fighter'","vc":0},{"name":"RECRUITED_'Elvish Archer''Elvish Scout''Elvish Fighter'Wose","vc":0},{"name":"RECRUITED_'Elvish Archer''Elvish Scout''Elvish Fighter'Wose'Elvish Shaman'","vc":0},{"name":"RECRUITED_'Elvish Archer''Elvish Scout''Elvish Fighter'Wose'Elvish Shaman''Merman Hunter'","vc":0},{"name":"RECRUITED_'Elvish Archer''Elvish Scout''Elvish Fighter'Wose'Elvish Shaman''Merman Hunter'Mage","vc":0},{"name":"enemy faction_Rebels","vc":0},{"name":"enemy faction_RebelsNortherners","vc":0},{"name":"enemy faction_RebelsNorthernersLoyalists","vc":0},{"name":"enemy faction_RebelsNorthernersLoyalistsDrakes","vc":0},{"name":"enemy faction_RebelsNorthernersLoyalistsDrakes'Knalgan Alliance'","vc":0},{"name":"enemy faction_RebelsNorthernersLoyalistsDrakes'Knalgan Alliance'Undead","vc":0},{"name":"closest enemy to leader","vc":0},{"name":"enemy Bone Shooter","vc":0},{"name":"enemy Bowman","vc":0},{"name":"enemy Cavalryman","vc":0},{"name":"enemy Dark Adept","vc":0},{"name":"enemy Dark Sorcerer","vc":0},{"name":"enemy Deathblade","vc":0},{"name":"enemy Drake Arbiter","vc":0},{"name":"enemy Drake Burner","vc":0},{"name":"enemy Drake Clasher","vc":0},{"name":"enemy Drake Fighter","vc":0},{"name":"enemy Drake Flare","vc":0},{"name":"enemy Drake Glider","vc":0},{"name":"enemy Drake Thrasher","vc":0},{"name":"enemy Drake Warrior","vc":0},{"name":"enemy Dwarvish Fighter","vc":0},{"name":"enemy Dwarvish Guardsman","vc":0},{"name":"enemy Dwarvish Stalwart","vc":0},{"name":"enemy Dwarvish Steelclad","vc":0},{"name":"enemy Dwarvish Thunderer","vc":0},{"name":"enemy Dwarvish Thunderguard","vc":0},{"name":"enemy Dwarvish Ulfserker","vc":0},{"name":"enemy Elder Wose","vc":0},{"name":"enemy Elvish Archer","vc":0},{"name":"enemy Elvish Captain","vc":0},{"name":"enemy Elvish Druid","vc":0},{"name":"enemy Elvish Fighter","vc":0},{"name":"enemy Elvish Hero","vc":0},{"name":"enemy Elvish Marksman","vc":0},{"name":"enemy Elvish Ranger","vc":0},{"name":"enemy Elvish Scout","vc":0},{"name":"enemy Elvish Shaman","vc":0},{"name":"enemy Elvish Sorceress","vc":0},{"name":"enemy Fencer","vc":0},{"name":"enemy Fire Drake","vc":0},{"name":"enemy Footpad","vc":0},{"name":"enemy Ghost","vc":0},{"name":"enemy Ghoul","vc":0},{"name":"enemy Goblin Impaler","vc":0},{"name":"enemy Goblin Spearman","vc":0},{"name":"enemy Gryphon Rider","vc":0},{"name":"enemy Heavy Infantryman","vc":0},{"name":"enemy Horseman","vc":0},{"name":"enemy Javelineer","vc":0},{"name":"enemy Lancer","vc":0},{"name":"enemy Lieutenant","vc":0},{"name":"enemy Longbowman","vc":0},{"name":"enemy Mage","vc":0},{"name":"enemy Merman Fighter","vc":0},{"name":"enemy Merman Hunter","vc":0},{"name":"enemy Merman Netcaster","vc":0},{"name":"enemy Naga Fighter","vc":0},{"name":"enemy Orcish Archer","vc":0},{"name":"enemy Orcish Assassin","vc":0},{"name":"enemy Orcish Crossbowman","vc":0},{"name":"enemy Orcish Grunt","vc":0},{"name":"enemy Orcish Slayer","vc":0},{"name":"enemy Orcish Warrior","vc":0},{"name":"enemy Outlaw","vc":0},{"name":"enemy Pikeman","vc":0},{"name":"enemy Poacher","vc":0},{"name":"enemy Red Mage","vc":0},{"name":"enemy Revenant","vc":0},{"name":"enemy Rogue","vc":0},{"name":"enemy Saurian Augur","vc":0},{"name":"enemy Saurian Oracle","vc":0},{"name":"enemy Saurian Skirmisher","vc":0},{"name":"enemy Saurian Soothsayer","vc":0},{"name":"enemy Shock Trooper","vc":0},{"name":"enemy Skeleton","vc":0},{"name":"enemy Skeleton Archer","vc":0},{"name":"enemy Soulless","vc":0},{"name":"enemy Spearman","vc":0},{"name":"enemy Swordsman","vc":0},{"name":"enemy Tentacle of the Deep","vc":0},{"name":"enemy Thief","vc":0},{"name":"enemy Trapper","vc":0},{"name":"enemy Troll","vc":0},{"name":"enemy Troll Rocklobber","vc":0},{"name":"enemy Troll Whelp","vc":0},{"name":"enemy Vampire Bat","vc":0},{"name":"enemy Walking Corpse","vc":0},{"name":"enemy White Mage","vc":0},{"name":"enemy Wolf Rider","vc":0},{"name":"enemy Wose","vc":0},{"name":"enemy Wraith","vc":0},{"name":"enemy gold","vc":0},{"name":"enemy leader hp pct","vc":0},{"name":"enemy level3+","vc":0},{"name":"enemy total-gold","vc":0},{"name":"enemy unit-gold","vc":0},{"name":"friendly Elder Wose","vc":0},{"name":"friendly Elvish Archer","vc":0},{"name":"friendly Elvish Captain","vc":0},{"name":"friendly Elvish Druid","vc":0},{"name":"friendly Elvish Fighter","vc":0},{"name":"friendly Elvish Hero","vc":0},{"name":"friendly Elvish Marksman","vc":0},{"name":"friendly Elvish Ranger","vc":0},{"name":"friendly Elvish Scout","vc":0},{"name":"friendly Elvish Shaman","vc":0},{"name":"friendly Elvish Sorceress","vc":0},{"name":"friendly Mage","vc":0},{"name":"friendly Merman Hunter","vc":0},{"name":"friendly Merman Netcaster","vc":0},{"name":"friendly Red Mage","vc":0},{"name":"friendly White Mage","vc":0},{"name":"friendly Wose","vc":0},{"name":"friendly gold","vc":0},{"name":"friendly leader hp pct","vc":0},{"name":"friendly total-gold","vc":0},{"name":"friendly unit-gold","vc":0},{"name":"side","vc":0},{"name":"terrain-forest","vc":0},{"name":"terrain-map-size","vc":0},{"name":"terrain-mountain-hill","vc":0},{"name":"terrain-water-swamp","vc":0},{"name":"time of day","vc":0},{"name":"total-gold-ratio","vc":0},{"name":"turn","vc":0},{"name":"village-control-margin","vc":0},{"name":"village-control-ratio","vc":0},{"name":"village-enemy","vc":0},{"name":"village-friendly","vc":0},{"name":"village-neutral","vc":0},{"name":"enemy Blood Bat","vc":0},{"name":"enemy Dragoon","vc":0},{"name":"enemy Elvish Rider","vc":0},{"name":"enemy Goblin Rouser","vc":0},{"name":"enemy Gryphon Master","vc":0},{"name":"enemy Knight","vc":0},{"name":"enemy Merman Spearman","vc":0},{"name":"enemy Merman Warrior","vc":0},{"name":"enemy Naga Warrior","vc":0},{"name":"enemy Saurian Ambusher","vc":0},{"name":"enemy Shadow","vc":0},{"name":"enemy Sky Drake","vc":0},{"name":"friendly Elvish Rider","vc":0},{"name":"friendly Merman Spearman","vc":0},{"name":"enemy Goblin Pillager","vc":0},{"name":"enemy Goblin Knight","vc":0},{"name":"enemy Necrophage","vc":0},{"name":"enemy Dwarvish Berserker","vc":0}]},"valueCap":16,"pu":false},"second":{"class":"GNormalize","before":{"name":"Untitled","attrs":[{"name":"RECRUITED_'Elvish Archer'","vc":0},{"name":"RECRUITED_'Elvish Archer''Elvish Scout'","vc":0},{"name":"RECRUITED_'Elvish Archer''Elvish Scout''Elvish Fighter'","vc":0},{"name":"RECRUITED_'Elvish Archer''Elvish Scout''Elvish Fighter'Wose","vc":0},{"name":"RECRUITED_'Elvish Archer''Elvish Scout''Elvish Fighter'Wose'Elvish Shaman'","vc":0},{"name":"RECRUITED_'Elvish Archer''Elvish Scout''Elvish Fighter'Wose'Elvish Shaman''Merman Hunter'","vc":0},{"name":"RECRUITED_'Elvish Archer''Elvish Scout''Elvish Fighter'Wose'Elvish Shaman''Merman Hunter'Mage","vc":0},{"name":"enemy faction_Rebels","vc":0},{"name":"enemy faction_RebelsNortherners","vc":0},{"name":"enemy faction_RebelsNorthernersLoyalists","vc":0},{"name":"enemy faction_RebelsNorthernersLoyalistsDrakes","vc":0},{"name":"enemy faction_RebelsNorthernersLoyalistsDrakes'Knalgan Alliance'","vc":0},{"name":"enemy faction_RebelsNorthernersLoyalistsDrakes'Knalgan Alliance'Undead","vc":0},{"name":"closest enemy to leader","vc":0},{"name":"enemy Bone Shooter","vc":0},{"name":"enemy Bowman","vc":0},{"name":"enemy Cavalryman","vc":0},{"name":"enemy Dark Adept","vc":0},{"name":"enemy Dark Sorcerer","vc":0},{"name":"enemy Deathblade","vc":0},{"name":"enemy Drake Arbiter","vc":0},{"name":"enemy Drake Burner","vc":0},{"name":"enemy Drake Clasher","vc":0},{"name":"enemy Drake Fighter","vc":0},{"name":"enemy Drake Flare","vc":0},{"name":"enemy Drake Glider","vc":0},{"name":"enemy Drake Thrasher","vc":0},{"name":"enemy Drake Warrior","vc":0},{"name":"enemy Dwarvish Fighter","vc":0},{"name":"enemy Dwarvish Guardsman","vc":0},{"name":"enemy Dwarvish Stalwart","vc":0},{"name":"enemy Dwarvish Steelclad","vc":0},{"name":"enemy Dwarvish Thunderer","vc":0},{"name":"enemy Dwarvish Thunderguard","vc":0},{"name":"enemy Dwarvish Ulfserker","vc":0},{"name":"enemy Elder Wose","vc":0},{"name":"enemy Elvish Archer","vc":0},{"name":"enemy Elvish Captain","vc":0},{"name":"enemy Elvish Druid","vc":0},{"name":"enemy Elvish Fighter","vc":0},{"name":"enemy Elvish Hero","vc":0},{"name":"enemy Elvish Marksman","vc":0},{"name":"enemy Elvish Ranger","vc":0},{"name":"enemy Elvish Scout","vc":0},{"name":"enemy Elvish Shaman","vc":0},{"name":"enemy Elvish Sorceress","vc":0},{"name":"enemy Fencer","vc":0},{"name":"enemy Fire Drake","vc":0},{"name":"enemy Footpad","vc":0},{"name":"enemy Ghost","vc":0},{"name":"enemy Ghoul","vc":0},{"name":"enemy Goblin Impaler","vc":0},{"name":"enemy Goblin Spearman","vc":0},{"name":"enemy Gryphon Rider","vc":0},{"name":"enemy Heavy Infantryman","vc":0},{"name":"enemy Horseman","vc":0},{"name":"enemy Javelineer","vc":0},{"name":"enemy Lancer","vc":0},{"name":"enemy Lieutenant","vc":0},{"name":"enemy Longbowman","vc":0},{"name":"enemy Mage","vc":0},{"name":"enemy Merman Fighter","vc":0},{"name":"enemy Merman Hunter","vc":0},{"name":"enemy Merman Netcaster","vc":0},{"name":"enemy Naga Fighter","vc":0},{"name":"enemy Orcish Archer","vc":0},{"name":"enemy Orcish Assassin","vc":0},{"name":"enemy Orcish Crossbowman","vc":0},{"name":"enemy Orcish Grunt","vc":0},{"name":"enemy Orcish Slayer","vc":0},{"name":"enemy Orcish Warrior","vc":0},{"name":"enemy Outlaw","vc":0},{"name":"enemy Pikeman","vc":0},{"name":"enemy Poacher","vc":0},{"name":"enemy Red Mage","vc":0},{"name":"enemy Revenant","vc":0},{"name":"enemy Rogue","vc":0},{"name":"enemy Saurian Augur","vc":0},{"name":"enemy Saurian Oracle","vc":0},{"name":"enemy Saurian Skirmisher","vc":0},{"name":"enemy Saurian Soothsayer","vc":0},{"name":"enemy Shock Trooper","vc":0},{"name":"enemy Skeleton","vc":0},{"name":"enemy Skeleton Archer","vc":0},{"name":"enemy Soulless","vc":0},{"name":"enemy Spearman","vc":0},{"name":"enemy Swordsman","vc":0},{"name":"enemy Tentacle of the Deep","vc":0},{"name":"enemy Thief","vc":0},{"name":"enemy Trapper","vc":0},{"name":"enemy Troll","vc":0},{"name":"enemy Troll Rocklobber","vc":0},{"name":"enemy Troll Whelp","vc":0},{"name":"enemy Vampire Bat","vc":0},{"name":"enemy Walking Corpse","vc":0},{"name":"enemy White Mage","vc":0},{"name":"enemy Wolf Rider","vc":0},{"name":"enemy Wose","vc":0},{"name":"enemy Wraith","vc":0},{"name":"enemy gold","vc":0},{"name":"enemy leader hp pct","vc":0},{"name":"enemy level3+","vc":0},{"name":"enemy total-gold","vc":0},{"name":"enemy unit-gold","vc":0},{"name":"friendly Elder Wose","vc":0},{"name":"friendly Elvish Archer","vc":0},{"name":"friendly Elvish Captain","vc":0},{"name":"friendly Elvish Druid","vc":0},{"name":"friendly Elvish Fighter","vc":0},{"name":"friendly Elvish Hero","vc":0},{"name":"friendly Elvish Marksman","vc":0},{"name":"friendly Elvish Ranger","vc":0},{"name":"friendly Elvish Scout","vc":0},{"name":"friendly Elvish Shaman","vc":0},{"name":"friendly Elvish Sorceress","vc":0},{"name":"friendly Mage","vc":0},{"name":"friendly Merman Hunter","vc":0},{"name":"friendly Merman Netcaster","vc":0},{"name":"friendly Red Mage","vc":0},{"name":"friendly White Mage","vc":0},{"name":"friendly Wose","vc":0},{"name":"friendly gold","vc":0},{"name":"friendly leader hp pct","vc":0},{"name":"friendly total-gold","vc":0},{"name":"friendly unit-gold","vc":0},{"name":"side","vc":0},{"name":"terrain-forest","vc":0},{"name":"terrain-map-size","vc":0},{"name":"terrain-mountain-hill","vc":0},{"name":"terrain-water-swamp","vc":0},{"name":"time of day","vc":0},{"name":"total-gold-ratio","vc":0},{"name":"turn","vc":0},{"name":"village-control-margin","vc":0},{"name":"village-control-ratio","vc":0},{"name":"village-enemy","vc":0},{"name":"village-friendly","vc":0},{"name":"village-neutral","vc":0},{"name":"enemy Blood Bat","vc":0},{"name":"enemy Dragoon","vc":0},{"name":"enemy Elvish Rider","vc":0},{"name":"enemy Goblin Rouser","vc":0},{"name":"enemy Gryphon Master","vc":0},{"name":"enemy Knight","vc":0},{"name":"enemy Merman Spearman","vc":0},{"name":"enemy Merman Warrior","vc":0},{"name":"enemy Naga Warrior","vc":0},{"name":"enemy Saurian Ambusher","vc":0},{"name":"enemy Shadow","vc":0},{"name":"enemy Sky Drake","vc":0},{"name":"friendly Elvish Rider","vc":0},{"name":"friendly Merman Spearman","vc":0},{"name":"enemy Goblin Pillager","vc":0},{"name":"enemy Goblin Knight","vc":0},{"name":"enemy Necrophage","vc":0},{"name":"enemy Dwarvish Berserker","vc":0}]},"after":{"name":"Untitled","attrs":[{"name":"RECRUITED_'Elvish Archer'","vc":0},{"name":"RECRUITED_'Elvish Archer''Elvish Scout'","vc":0},{"name":"RECRUITED_'Elvish Archer''Elvish Scout''Elvish Fighter'","vc":0},{"name":"RECRUITED_'Elvish Archer''Elvish Scout''Elvish Fighter'Wose","vc":0},{"name":"RECRUITED_'Elvish Archer''Elvish Scout''Elvish Fighter'Wose'Elvish Shaman'","vc":0},{"name":"RECRUITED_'Elvish Archer''Elvish Scout''Elvish Fighter'Wose'Elvish Shaman''Merman Hunter'","vc":0},{"name":"RECRUITED_'Elvish Archer''Elvish Scout''Elvish Fighter'Wose'Elvish Shaman''Merman Hunter'Mage","vc":0},{"name":"enemy faction_Rebels","vc":0},{"name":"enemy faction_RebelsNortherners","vc":0},{"name":"enemy faction_RebelsNorthernersLoyalists","vc":0},{"name":"enemy faction_RebelsNorthernersLoyalistsDrakes","vc":0},{"name":"enemy faction_RebelsNorthernersLoyalistsDrakes'Knalgan Alliance'","vc":0},{"name":"enemy faction_RebelsNorthernersLoyalistsDrakes'Knalgan Alliance'Undead","vc":0},{"name":"closest enemy to leader","vc":0},{"name":"enemy Bone Shooter","vc":0},{"name":"enemy Bowman","vc":0},{"name":"enemy Cavalryman","vc":0},{"name":"enemy Dark Adept","vc":0},{"name":"enemy Dark Sorcerer","vc":0},{"name":"enemy Deathblade","vc":0},{"name":"enemy Drake Arbiter","vc":0},{"name":"enemy Drake Burner","vc":0},{"name":"enemy Drake Clasher","vc":0},{"name":"enemy Drake Fighter","vc":0},{"name":"enemy Drake Flare","vc":0},{"name":"enemy Drake Glider","vc":0},{"name":"enemy Drake Thrasher","vc":0},{"name":"enemy Drake Warrior","vc":0},{"name":"enemy Dwarvish Fighter","vc":0},{"name":"enemy Dwarvish Guardsman","vc":0},{"name":"enemy Dwarvish Stalwart","vc":0},{"name":"enemy Dwarvish Steelclad","vc":0},{"name":"enemy Dwarvish Thunderer","vc":0},{"name":"enemy Dwarvish Thunderguard","vc":0},{"name":"enemy Dwarvish Ulfserker","vc":0},{"name":"enemy Elder Wose","vc":0},{"name":"enemy Elvish Archer","vc":0},{"name":"enemy Elvish Captain","vc":0},{"name":"enemy Elvish Druid","vc":0},{"name":"enemy Elvish Fighter","vc":0},{"name":"enemy Elvish Hero","vc":0},{"name":"enemy Elvish Marksman","vc":0},{"name":"enemy Elvish Ranger","vc":0},{"name":"enemy Elvish Scout","vc":0},{"name":"enemy Elvish Shaman","vc":0},{"name":"enemy Elvish Sorceress","vc":0},{"name":"enemy Fencer","vc":0},{"name":"enemy Fire Drake","vc":0},{"name":"enemy Footpad","vc":0},{"name":"enemy Ghost","vc":0},{"name":"enemy Ghoul","vc":0},{"name":"enemy Goblin Impaler","vc":0},{"name":"enemy Goblin Spearman","vc":0},{"name":"enemy Gryphon Rider","vc":0},{"name":"enemy Heavy Infantryman","vc":0},{"name":"enemy Horseman","vc":0},{"name":"enemy Javelineer","vc":0},{"name":"enemy Lancer","vc":0},{"name":"enemy Lieutenant","vc":0},{"name":"enemy Longbowman","vc":0},{"name":"enemy Mage","vc":0},{"name":"enemy Merman Fighter","vc":0},{"name":"enemy Merman Hunter","vc":0},{"name":"enemy Merman Netcaster","vc":0},{"name":"enemy Naga Fighter","vc":0},{"name":"enemy Orcish Archer","vc":0},{"name":"enemy Orcish Assassin","vc":0},{"name":"enemy Orcish Crossbowman","vc":0},{"name":"enemy Orcish Grunt","vc":0},{"name":"enemy Orcish Slayer","vc":0},{"name":"enemy Orcish Warrior","vc":0},{"name":"enemy Outlaw","vc":0},{"name":"enemy Pikeman","vc":0},{"name":"enemy Poacher","vc":0},{"name":"enemy Red Mage","vc":0},{"name":"enemy Revenant","vc":0},{"name":"enemy Rogue","vc":0},{"name":"enemy Saurian Augur","vc":0},{"name":"enemy Saurian Oracle","vc":0},{"name":"enemy Saurian Skirmisher","vc":0},{"name":"enemy Saurian Soothsayer","vc":0},{"name":"enemy Shock Trooper","vc":0},{"name":"enemy Skeleton","vc":0},{"name":"enemy Skeleton Archer","vc":0},{"name":"enemy Soulless","vc":0},{"name":"enemy Spearman","vc":0},{"name":"enemy Swordsman","vc":0},{"name":"enemy Tentacle of the Deep","vc":0},{"name":"enemy Thief","vc":0},{"name":"enemy Trapper","vc":0},{"name":"enemy Troll","vc":0},{"name":"enemy Troll Rocklobber","vc":0},{"name":"enemy Troll Whelp","vc":0},{"name":"enemy Vampire Bat","vc":0},{"name":"enemy Walking Corpse","vc":0},{"name":"enemy White Mage","vc":0},{"name":"enemy Wolf Rider","vc":0},{"name":"enemy Wose","vc":0},{"name":"enemy Wraith","vc":0},{"name":"enemy gold","vc":0},{"name":"enemy leader hp pct","vc":0},{"name":"enemy level3+","vc":0},{"name":"enemy total-gold","vc":0},{"name":"enemy unit-gold","vc":0},{"name":"friendly Elder Wose","vc":0},{"name":"friendly Elvish Archer","vc":0},{"name":"friendly Elvish Captain","vc":0},{"name":"friendly Elvish Druid","vc":0},{"name":"friendly Elvish Fighter","vc":0},{"name":"friendly Elvish Hero","vc":0},{"name":"friendly Elvish Marksman","vc":0},{"name":"friendly Elvish Ranger","vc":0},{"name":"friendly Elvish Scout","vc":0},{"name":"friendly Elvish Shaman","vc":0},{"name":"friendly Elvish Sorceress","vc":0},{"name":"friendly Mage","vc":0},{"name":"friendly Merman Hunter","vc":0},{"name":"friendly Merman Netcaster","vc":0},{"name":"friendly Red Mage","vc":0},{"name":"friendly White Mage","vc":0},{"name":"friendly Wose","vc":0},{"name":"friendly gold","vc":0},{"name":"friendly leader hp pct","vc":0},{"name":"friendly total-gold","vc":0},{"name":"friendly unit-gold","vc":0},{"name":"side","vc":0},{"name":"terrain-forest","vc":0},{"name":"terrain-map-size","vc":0},{"name":"terrain-mountain-hill","vc":0},{"name":"terrain-water-swamp","vc":0},{"name":"time of day","vc":0},{"name":"total-gold-ratio","vc":0},{"name":"turn","vc":0},{"name":"village-control-margin","vc":0},{"name":"village-control-ratio","vc":0},{"name":"village-enemy","vc":0},{"name":"village-friendly","vc":0},{"name":"village-neutral","vc":0},{"name":"enemy Blood Bat","vc":0},{"name":"enemy Dragoon","vc":0},{"name":"enemy Elvish Rider","vc":0},{"name":"enemy Goblin Rouser","vc":0},{"name":"enemy Gryphon Master","vc":0},{"name":"enemy Knight","vc":0},{"name":"enemy Merman Spearman","vc":0},{"name":"enemy Merman Warrior","vc":0},{"name":"enemy Naga Warrior","vc":0},{"name":"enemy Saurian Ambusher","vc":0},{"name":"enemy Shadow","vc":0},{"name":"enemy Sky Drake","vc":0},{"name":"friendly Elvish Rider","vc":0},{"name":"friendly Merman Spearman","vc":0},{"name":"enemy Goblin Pillager","vc":0},{"name":"enemy Goblin Knight","vc":0},{"name":"enemy Necrophage","vc":0},{"name":"enemy Dwarvish Berserker","vc":0}]},"min":-1.5,"max":1.5,"mins":[0,0,0,0,0,0,0,0,0,0,0,0,0,1,0,0,0,0,0,0,0,0,0,0,0,0,0,0,0,0,0,0,0,0,0,0,0,0,0,0,0,0,0,0,0,0,0,0,0,0,0,0,0,0,0,0,0,0,0,0,0,0,0,0,0,0,0,0,0,0,0,0,0,0,0,0,0,0,0,0,0,0,0,0,0,0,0,0,0,0,0,0,0,0,0,0,0,0,0,-7,0.016,0,26,24,0,0,0,0,0,0,0,0,0,0,0,0,0,0,0,0,0,14,0.02,60,46,1,0.04,588,0.012,0.058,1,0.06,1,-44,0,0,0,0,0,0,0,0,0,0,0,0,0,0,0,0,0,0,0,0,0,0],"ranges":[1,1,1,1,1,1,1,1,1,1,1,1,1,56,2,7,29,17,2,2,1,11,13,32,2,25,2,2,12,14,2,2,15,3,8,4,8,2,1,15,2,2,1,34,9,1,7,1,28,25,22,2,35,23,13,20,1,1,1,2,11,15,10,1,20,12,12,3,21,1,2,1,2,17,1,2,2,19,1,12,2,1,9,20,1,26,2,1,24,2,2,2,15,34,15,1,11,14,1,182,0.984,2,1007,994,8,38,2,2,22,2,2,2,41,14,2,15,17,1,2,2,20,169,0.98,1286,1263,1,0.123,1574,0.196,0.301,5,0.916,47,88,1,44,44,42,2,1,1,2,1,1,1,1,2,2,1,1,3,2,1,1,1,1]}},"_fl":{"class":"GNormalize","before":{"name":"__temp0.csv","attrs":[{"name":"future gold yield+2vc","vc":0}]},"after":{"name":"__temp0.csv","attrs":[{"name":"future gold yield+2vc","vc":0}]},"min":0,"max":1,"mins":[-10.444],"ranges":[304.172]},"_rf":{"name":"__temp0.csv","attrs":[{"name":"RECRUITED","vals":["Elvish Archer","Elvish Scout","Elvish Fighter","Wose","Elvish Shaman","Merman Hunter","Mage"]},{"name":"enemy faction","vals":["Rebels","Northerners","Loyalists","Drakes","Knalgan Alliance","Undead"]},{"name":"closest enemy to leader","vc":0},{"name":"enemy Bone Shooter","vc":0},{"name":"enemy Bowman","vc":0},{"name":"enemy Cavalryman","vc":0},{"name":"enemy Dark Adept","vc":0},{"name":"enemy Dark Sorcerer","vc":0},{"name":"enemy Deathblade","vc":0},{"name":"enemy Drake Arbiter","vc":0},{"name":"enemy Drake Burner","vc":0},{"name":"enemy Drake Clasher","vc":0},{"name":"enemy Drake Fighter","vc":0},{"name":"enemy Drake Flare","vc":0},{"name":"enemy Drake Glider","vc":0},{"name":"enemy Drake Thrasher","vc":0},{"name":"enemy Drake Warrior","vc":0},{"name":"enemy Dwarvish Fighter","vc":0},{"name":"enemy Dwarvish Guardsman","vc":0},{"name":"enemy Dwarvish Stalwart","vc":0},{"name":"enemy Dwarvish Steelclad","vc":0},{"name":"enemy Dwarvish Thunderer","vc":0},{"name":"enemy Dwarvish Thunderguard","vc":0},{"name":"enemy Dwarvish Ulfserker","vc":0},{"name":"enemy Elder Wose","vc":0},{"name":"enemy Elvish Archer","vc":0},{"name":"enemy Elvish Captain","vc":0},{"name":"enemy Elvish Druid","vc":0},{"name":"enemy Elvish Fighter","vc":0},{"name":"enemy Elvish Hero","vc":0},{"name":"enemy Elvish Marksman","vc":0},{"name":"enemy Elvish Ranger","vc":0},{"name":"enemy Elvish Scout","vc":0},{"name":"enemy Elvish Shaman","vc":0},{"name":"enemy Elvish Sorceress","vc":0},{"name":"enemy Fencer","vc":0},{"name":"enemy Fire Drake","vc":0},{"name":"enemy Footpad","vc":0},{"name":"enemy Ghost","vc":0},{"name":"enemy Ghoul","vc":0},{"name":"enemy Goblin Impaler","vc":0},{"name":"enemy Goblin Spearman","vc":0},{"name":"enemy Gryphon Rider","vc":0},{"name":"enemy Heavy Infantryman","vc":0},{"name":"enemy Horseman","vc":0},{"name":"enemy Javelineer","vc":0},{"name":"enemy Lancer","vc":0},{"name":"enemy Lieutenant","vc":0},{"name":"enemy Longbowman","vc":0},{"name":"enemy Mage","vc":0},{"name":"enemy Merman Fighter","vc":0},{"name":"enemy Merman Hunter","vc":0},{"name":"enemy Merman Netcaster","vc":0},{"name":"enemy Naga Fighter","vc":0},{"name":"enemy Orcish Archer","vc":0},{"name":"enemy Orcish Assassin","vc":0},{"name":"enemy Orcish Crossbowman","vc":0},{"name":"enemy Orcish Grunt","vc":0},{"name":"enemy Orcish Slayer","vc":0},{"name":"enemy Orcish Warrior","vc":0},{"name":"enemy Outlaw","vc":0},{"name":"enemy Pikeman","vc":0},{"name":"enemy Poacher","vc":0},{"name":"enemy Red Mage","vc":0},{"name":"enemy Revenant","vc":0},{"name":"enemy Rogue","vc":0},{"name":"enemy Saurian Augur","vc":0},{"name":"enemy Saurian Oracle","vc":0},{"name":"enemy Saurian Skirmisher","vc":0},{"name":"enemy Saurian Soothsayer","vc":0},{"name":"enemy Shock Trooper","vc":0},{"name":"enemy Skeleton","vc":0},{"name":"enemy Skeleton Archer","vc":0},{"name":"enemy Soulless","vc":0},{"name":"enemy Spearman","vc":0},{"name":"enemy Swordsman","vc":0},{"name":"enemy Tentacle of the Deep","vc":0},{"name":"enemy Thief","vc":0},{"name":"enemy Trapper","vc":0},{"name":"enemy Troll","vc":0},{"name":"enemy Troll Rocklobber","vc":0},{"name":"enemy Troll Whelp","vc":0},{"name":"enemy Vampire Bat","vc":0},{"name":"enemy Walking Corpse","vc":0},{"name":"enemy White Mage","vc":0},{"name":"enemy Wolf Rider","vc":0},{"name":"enemy Wose","vc":0},{"name":"enemy Wraith","vc":0},{"name":"enemy gold","vc":0},{"name":"enemy leader hp pct","vc":0},{"name":"enemy level3+","vc":0},{"name":"enemy total-gold","vc":0},{"name":"enemy unit-gold","vc":0},{"name":"friendly Elder Wose","vc":0},{"name":"friendly Elvish Archer","vc":0},{"name":"friendly Elvish Captain","vc":0},{"name":"friendly Elvish Druid","vc":0},{"name":"friendly Elvish Fighter","vc":0},{"name":"friendly Elvish Hero","vc":0},{"name":"friendly Elvish Marksman","vc":0},{"name":"friendly Elvish Ranger","vc":0},{"name":"friendly Elvish Scout","vc":0},{"name":"friendly Elvish Shaman","vc":0},{"name":"friendly Elvish Sorceress","vc":0},{"name":"friendly Mage","vc":0},{"name":"friendly Merman Hunter","vc":0},{"name":"friendly Merman Netcaster","vc":0},{"name":"friendly Red Mage","vc":0},{"name":"friendly White Mage","vc":0},{"name":"friendly Wose","vc":0},{"name":"friendly gold","vc":0},{"name":"friendly leader hp pct","vc":0},{"name":"friendly total-gold","vc":0},{"name":"friendly unit-gold","vc":0},{"name":"side","vc":0},{"name":"terrain-forest","vc":0},{"name":"terrain-map-size","vc":0},{"name":"terrain-mountain-hill","vc":0},{"name":"terrain-water-swamp","vc":0},{"name":"time of day","vc":0},{"name":"total-gold-ratio","vc":0},{"name":"turn","vc":0},{"name":"village-control-margin","vc":0},{"name":"village-control-ratio","vc":0},{"name":"village-enemy","vc":0},{"name":"village-friendly","vc":0},{"name":"village-neutral","vc":0},{"name":"enemy Blood Bat","vc":0},{"name":"enemy Dragoon","vc":0},{"name":"enemy Elvish Rider","vc":0},{"name":"enemy Goblin Rouser","vc":0},{"name":"enemy Gryphon Master","vc":0},{"name":"enemy Knight","vc":0},{"name":"enemy Merman Spearman","vc":0},{"name":"enemy Merman Warrior","vc":0},{"name":"enemy Naga Warrior","vc":0},{"name":"enemy Saurian Ambusher","vc":0},{"name":"enemy Shadow","vc":0},{"name":"enemy Sky Drake","vc":0},{"name":"friendly Elvish Rider","vc":0},{"name":"friendly Merman Spearman","vc":0},{"name":"enemy Goblin Pillager","vc":0},{"name":"enemy Goblin Knight","vc":0},{"name":"enemy Necrophage","vc":0},{"name":"enemy Dwarvish Berserker","vc":0}]},"_rl":{"name":"__temp0.csv","attrs":[{"name":"future gold yield+2vc","vc":0}]},"ifd":156,"layers":[{"nodes":14,"af":"logistic"},{"nodes":1}],"learningRate":0.1,"momentum":0,"target":0,"ib":false,"weights":[-0.18024568692698,0.1914079278396,-0.12346208924442,0.16454611891596,-0.16466438019085,0.16313405686967,0.034544237134383,-0.19825949845211,-0.153932254884,0.1348270069236,-0.26341228439371,0.018655879469697,0.26106273075228,-0.27169411960754,0.13721985570766,0.096593933982157,-0.062427847855883,0.087470574267992,0.23252029912839,0.058920866682403,0.080544928111776,-0.053134448508048,-0.15477608725702,0.14748041931608,0.13882759041965,-0.16053565847999,-0.035369876597735,0.048044719237321,0.091243895725073,0.22679717414914,-0.18683059572866,0.19122824948029,-0.17748442033109,0.17310907081589,-0.15580222155946,0.021517778902406,-0.031516875900996,-0.15219527614574,0.015147307308722,-0.11768856179935,0.43645807058913,0.05145350453799,0.087392763078587,-0.27949682667765,-0.3469549896385,0.06995601348834,0.0092409518505544,-0.1875943193132,0.11850312155771,-0.019677382739907,-0.14447853513897,0.090922122365717,0.017536389273806,0.063003737238729,-0.14859022002101,0.089779538539051,0.10575956943597,0.11130610957769,-0.14798173395395,-0.21053972684392,0.2919902006369,0.44399294403426,-0.29122426306951,0.247704118552,0.0093027717208168,-0.13280322568059,0.15128304706599,-0.21170649407458,0.042853626608741,0.42006788619821,0.081191626023181,0.04434234041322,0.081306444102583,-0.082595122175489,0.14835407520112,-0.11508672894822,0.058956359684114,0.14276919480229,0.20615412322257,-0.0064595552140495,-0.14144310473454,-0.084035858381328,0.036203199918296,0.039423267464297,-0.22053277702057,-0.24780351116422,-0.20147389847616,-0.057931570959186,0.1595353103529,-0.11689548975654,0.42235240053066,-0.098680242364613,0.0078440446567015,-0.39511890498967,0.076782998560395,0.19207788324311,-0.074783280843388,-0.13176918118624,0.13303891301756,0.062374977444857,-0.30530688676841,0.26361107737699,-0.16091720048839,0.64406810235508,0.48767792274197,0.10225571315772,-0.27896838116342,-0.46336896284304,-0.21737033538434,-0.19153056315683,0.016701147413043,0.35294654109987,-0.068593401510999,-0.089734814144321,0.025781879497572,0.24533454108341,-0.026803626831886,0.19058501911498,-0.15743381622636,-0.22046914385806,0.13601982319031,0.18653384345699,-0.16985809545064,-0.41880477897528,-0.18605191730212,0.14429235026722,-0.65420021498579,0.057121003746677,0.5296748994957,0.15967302348359,-0.10081499209706,0.050224700101805,-0.47101377816711,0.37318347947529,-0.062409797483566,-0.15910443801777,0.24723295928768,-0.15217044649823,-0.24428667457735,0.20404568729403,-0.20886478599461,-0.0027366634999485,0.123084920335,-0.083251895365913,0.0067749011247027,-0.16705694290186,-0.017279184178189,-0.092019846228159,-0.093682301666435,-0.11402123390117,0.17729295689351,-0.061953561039287,-0.25207626518184,-0.031734466397121,-0.0047573716091545,-0.048327124404513,-0.057467697506271,0.63312482256833,-0.21437302480795,0.10842323545572,-0.32848918346031,-0.47938748133214,0.36750845778356,0.14512739410742,-0.13230691093987,0.013701386556093,0.39730918417492,-0.42225960266316,-0.13704903796382,-0.039619220473626,-0.0021010518706733,-0.32254122351155,0.21753696755804,-0.041217606685345,0.09865383409877,0.073574132358934,-0.16969255686861,0.23182624678161,-0.049541294822738,-0.011050649256125,0.048369757956885,0.25314584607404,-0.15740511400157,-0.035583155203831,-0.13423232364008,0.053943513351617,0.22045540719719,-0.074870256076327,-0.21155268656837,-0.0035290693207403,0.0009413750541476,0.073771984818781,-0.11127786375499,-0.12614986977608,0.050344397953254,0.15210484502859,-0.030825616630085,0.28381249624812,-0.0013823978837146,0.041871075086071,-0.16764209097876,-0.20974605951231,-0.019123370894612,-0.02095819604605,-0.089810773506488,0.081942613222515,0.070384643218077,0.078426159567633,0.008972289229868,-0.0077319952474258,0.079054427489276,-0.1261573092969,-0.094578951362784,0.034414212476917,-0.18262331898854,0.0067232250618896,-0.28623567736556,-0.030932176482298,0.12872825632935,-0.35374215954475,-0.015534494650618,-0.14844346389484,-0.011464992144319,0.20351334731535,-0.083887596846521,-0.087708120793767,-0.073148654003466,0.043014992863894,-0.046824136223738,0.13142026343334,-0.00025847996443415,0.14527453626144,0.095166374094034,-0.11554376914162,0.18951326371617,0.29020356452392,-0.092127920295224,0.17084022174958,0.068503163844887,0.0502053693086,0.3084387395995,0.010565643213335,-0.019683822621442,-0.20287527452341,-0.046627525200571,0.0070677898942892,-0.30703857947386,0.074653821909697,0.041479477036435,0.0073975276710068,0.04319695045361,0.070825136476865,0.1208932543535,0.014730828604522,0.00064428933528322,0.17241532039758,0.1123341688161,-0.1750692589743,-0.11769333862258,-0.36861015765621,-0.10737570219002,-0.10712019338352,0.11785890649076,0.033845091967499,-0.19437297151072,0.12167030334299,0.033524391193789,-0.1387159624672,-0.17020304711196,-0.089843934222413,0.10251983494796,0.1928303807947,-0.10182315120293,-0.19833952517806,0.28285282542678,-0.030870391244337,0.060813493475636,-0.19041671690874,-0.13291251430645,-0.10224596915312,-0.25895753546683,-0.012109220635341,-0.07200028677763,-0.33642463940876,0.071904912307541,-0.088262280614234,-0.056375460711109,0.107735599221,-0.18687575184698,0.092102373261612,0.55211004304379,-0.1156074592214,-0.043690584774323,0.10090025195139,0.21732723457649,-0.34454790140617,-0.23977525686392,0.12057166516201,-0.015917134170066,-0.21518213549442,-0.2092185999654,0.058993403646545,-0.13625853834482,-0.071502123461236,-0.031103684171996,0.0029227930601455,0.061013422769897,0.094143606583775,0.079743941172342,-0.12096304411162,0.057948739769526,0.11649942362012,0.022386429369319,-0.063239947771479,0.47172063130364,-0.080761014980064,-0.0081178135791108,0.073211621446795,0.00017362999448927,0.092329409592619,-0.12273987146082,0.0027199870746887,-0.049650722588968,-0.13049157298238,0.0046316415047352,0.016608567767346,0.08857777084426,0.027026690078559,-0.13735569571103,-0.0011489559285441,0.17881442966592,0.20002926449856,-0.1067466409444,0.011720269099933,0.20071511068597,0.15702580746766,-0.096985469815377,0.31679084858591,0.14359978958886,-0.070146797499467,-0.05672506748302,-0.078520952638604,-0.034302060756451,0.013620780140808,-0.00095036440687172,0.023243510795123,0.12916596504416,0.012605044508813,0.042316773079085,0.14045610112705,0.089351027633189,-0.082110358932622,-0.087692362494285,-0.062903700832055,-0.16792712419515,0.15328618842679,0.13853550052917,-0.00069680966270464,-0.027114160010497,0.13521778454376,-0.058785761172324,-0.044548705547959,-0.16409789190984,0.07962301827942,0.065265975947858,-0.030103408230197,0.022313418051239,0.018785100244184,0.054316268720651,0.076176109658143,0.072165523647882,-0.043837383326747,-0.017932749340203,-0.039620363495805,-0.023864227891904,0.023638690856853,0.10902948083136,-0.01370240630693,-0.18384060328183,0.12928644379842,-0.073215042897672,0.08044215147037,-0.047899301767393,-0.016342363844942,-0.019940730089029,0.088810764091649,-0.070292638987534,-0.049615008322894,0.13090293756419,-0.077188985697614,-0.05883125540419,-0.090752408235351,0.047576372111693,0.042978328182992,0.19431146638982,-0.048272031130657,-0.052176604668871,-0.068337186632329,-0.025503470758279,-0.0067049545285182,0.021991356676111,0.097850298593284,0.19131450286307,0.17420360648855,-0.18743521641826,0.091419307087413,-0.022046443546478,-0.10338851703601,0.10187662201178,0.1078943733959,-0.14468258380229,-0.10520491956396,0.1359055404763,-0.024093679757388,0.11944235340674,-0.020191402139774,-0.010005861832874,-0.02411019159791,0.20343975852543,0.086205173850395,-0.14786148911383,-0.054250953358859,0.017779750734514,0.0049628416078204,0.11888134998396,0.10349214356778,-0.05177870840188,-0.0015158423467171,0.036180695373188,-0.022633096069437,-0.11505014876936,0.054775660014972,0.058821003690803,0.081196474656079,-0.012682553806966,-0.053733428715175,0.033224880764957,-0.053942945192766,-0.032647789623312,-0.084156199533998,-0.027716919677973,0.057765108208565,0.13944395670434,-0.022538072101613,0.037553228533859,-0.0012200673868984,0.14185833327023,0.077777800491662,-0.10867237292069,-0.083025685411291,0.052394070534398,-0.06452343798811,-0.10661678756526,0.092932660382595,0.1275822286024,-0.0016677745454705,-0.092592517718464,0.052096285313567,-0.00042397476891709,-0.029901735606966,0.011117349700636,0.16044937387621,-0.083882659889415,0.0034484419412007,-0.03425910432842,-0.033964728261588,-0.013799697318895,-0.13118671159154,0.038289583846124,-8.9011447425502e-05,0.091417149941748,-0.10759057822751,0.076479956775676,0.48071520321206,0.062142919130827,-0.45668324755621,0.26693341642281,0.38030444841226,-0.53469207322135,-0.023701115110604,0.13337562489672,0.20229189285478,-0.17494579243401,-0.071692836930748,0.021697277282799,-0.12431261678129,-0.087254409095711,0.24613536287415,-0.23093685940726,0.31060617525806,-0.052670127460749,0.23417864624761,0.026847104210688,0.00060048009187699,0.1563071171907,0.59321899963971,-0.12854457573173,-0.23811678409055,-0.019047442972989,0.0068512766547566,0.31940775237283,0.25017510335468,-0.11378449470188,-0.0028635218809276,0.37745756092589,0.087714039650328,0.0070218570728297,0.077142556084154,0.26522384033081,0.20174644169483,0.020026945648876,0.055048180186832,0.016711630647859,-0.089832114897222,-0.068850775812106,-0.31956642446178,-0.26732611886822,0.0086782730761923,0.29681102557043,-0.078872462924433,0.069001490161124,-0.056390269554062,0.10961459413621,-0.088639878524306,0.19147037854665,-0.032143630653986,0.00076737836470691,0.061769878914677,0.062365856465896,0.07581629002064,0.087748993932804,-0.13119442960735,0.11944025550801,-0.45048712412109,0.011613041311603,-0.041000045461262,0.0065292100519361,-0.0023748017005868,-0.074706887260109,0.039973467734472,0.49885367198317,-0.0027491341413343,-0.090077720806924,0.16066650310913,0.02095119347788,0.30119733610812,-0.084606275466411,0.074637150046007,0.13823679531503,0.10568025530205,0.065147195630692,0.13187390750673,0.037791147934549,-0.0084563670915196,0.19364006143103,0.44345719593641,0.12623064904048,0.30864203693957,-0.032390784153601,-0.20191604081165,-0.064064688261414,0.14704275961746,-0.029608763891237,-0.05473806805027,0.033982652704005,-0.40501308990369,-0.03916039236731,-0.10205897089254,-0.13470803693052,0.70707817382954,-0.38466518441163,-0.45679908480142,0.27599816347517,-0.81999735608387,0.17604151800006,0.41029645266841,0.15704247415279,-0.31792622694188,-0.075404519041037,0.0016019407159032,-0.26010127079143,-0.25587399494829,0.088369982361089,-0.025112772221036,0.30941498026238,-0.18670597234136,-0.17943217000411,-0.531131482119,-0.12081754055276,-0.19186721385973,-0.0095941937791278,-0.0059463032308196,-0.69493417867683,-0.11120442964173,-0.7568338247861,-0.5758838818208,-0.28783553888507,0.2000626925048,-0.21221199659296,-0.12253405014453,-0.19727537319761,0.5791238528114,0.16542318432876,-1.3237492972554,-0.033999596780655,0.01996321799556,-0.22864752797755,0.23877799727108,-0.49349695269238,0.036043192517105,0.29106287244455,0.0085747232831441,-0.018709323612399,-0.12862191724589,-0.15206039011783,-0.045181929908026,0.18837200643577,0.16812488682079,-0.17883477158019,0.17669589326532,0.13093421292251,0.12666413623088,-0.093587102899221,-0.052302445679108,-0.032562986630043,0.067256820508988,0.061300241041318,-0.019876062466161,0.28109383116138,-0.042087137099457,0.28836236510982,0.32177091755937,-0.58897419481871,0.097786428354114,-0.027087400453375,0.0091879047395322,0.33648059029017,0.04815373670556,-0.17393134799901,-0.13535266580771,0.071713519078944,-0.21050423789212,-0.075711425512154,-0.075927954908869,0.0046992427283079,-0.021100825220859,0.0063525093415994,0.11964263374068,0.054629006880547,-0.10842129414159,0.051652860037781,-0.039283349080289,0.12769428895886,-0.053657587407129,0.048958846011821,-0.18610508934643,0.040767905762537,0.027574679498571,-0.11691775393268,-0.099777582367639,0.25251648365655,0.047085169890426,0.033378732213756,-0.074803017387944,0.11097357543193,0.029289192817177,-0.202333290739,0.15959378753221,0.26726601088169,0.1004466564234,0.17571753199536,0.0613353049676,-0.07738072152188,0.10270630678141,0.10298728158332,-0.066474612902109,0.033780317875517,-0.036098836106259,-0.061477895241909,0.071226256794782,-0.068524258123256,-0.062638646663167,-0.015935449997596,0.067270802075658,-0.15990058841549,-0.23483772282447,-0.050727539577447,-0.078478253896035,-0.11203144697778,0.043188296243833,-0.20852603632204,-0.064095134669418,0.09092585040984,0.018395414969512,0.13593691102876,-0.01226683959904,-0.057340949090393,0.19893930201201,-0.17241958491393,0.080877699971895,-0.071531580968444,-0.20553925357907,-0.055671619215862,0.28956507017166,-0.071662643732264,0.20861599376508,-0.020419563446879,-0.013960466345817,0.10389287969908,-0.02437278993402,0.096738624324791,-0.042805446534647,0.13614588247491,0.19441457069374,-0.17581266267472,-0.18579844248289,0.11327009232471,-0.2896036347791,-0.1263086309832,0.10338001340511,0.13018822440293,-0.30137089511236,-0.057578227934105,0.1390782414398,0.16101336416202,-0.075559814302002,0.18690195141585,0.085454829460441,-0.084490534011522,0.22898202777287,-0.44448708249704,-0.031256907532022,-0.033580088714553,0.14886106632658,-0.028717355068228,0.056307177553473,0.0055695653769184,-0.1499500214534,0.067531090582385,0.14637918004891,-0.023957840530973,0.1902029053825,0.14267602813648,0.004139021535052,0.178161502828,0.033034963819495,0.024558591381871,-0.060518510489738,-0.20984418538835,-0.11244765607735,0.042787107692648,-0.20008230020682,0.15670457493922,0.19792306640814,0.16621259788364,0.12867273767399,-0.3047497463042,0.038688181112721,-0.42307004132554,-0.23020420479681,-0.056163734927758,-0.1039614253691,0.072188412801218,-0.0058096670296858,-0.14235443111847,-0.032291230765463,6.5092241138453e-05,0.10502805622853,-0.040573555208928,-0.0070785313380198,-0.24166323708467,-0.0069256407310484,-0.0021720337323293,-0.13933931257721,-0.072588162424833,-0.066388421088106,-0.0023331632257149,0.030028121657656,0.098124676600074,0.016364226931731,-0.0010428501583637,0.13371011892284,0.078668212791833,-0.027117510419602,-0.21033505052093,-0.89573016671246,0.077075248545096,-0.051049995066072,-0.24765952779728,0.13738877624741,0.12959181665895,-0.22801337458888,0.03549067615966,-0.015849656313491,0.06040849478886,-0.084141087071711,-0.12438613371135,-0.051953244740397,0.064732858094573,0.12055467647856,0.12522997771627,0.0074813353559177,0.13590855076525,-0.00079206696153832,-0.11734368697466,0.026638130568528,-0.13866944041624,-0.10439577100715,0.18054738538533,-0.031920482694247,-0.13484730668852,-0.065428401659591,0.0055797491100112,0.08141268370961,0.12649321246521,0.01118569006482,0.23528821162416,0.2089284260493,0.080272122357947,0.15358417292071,-0.098077134195306,-0.028836908917915,0.14072333851816,-0.017656441167904,0.17256203978007,-0.21297363042552,-0.027373359033112,0.18408616162775,-0.047373484914396,-0.047950369266864,0.047417608354091,-0.044753817458594,-0.060037386150906,0.13561856460347,0.00093999708944996,0.0042129737978923,-0.0083687955965663,-0.06381961564664,-0.085856982468789,0.10885278661216,0.010733578600589,0.11566705995939,0.059165502428246,-0.035823059061232,-0.054230214154438,0.18622330876265,-0.07650397324226,0.015816971371348,0.17182051804292,-0.022449458049998,-0.19632617974236,-0.022847217026027,0.044190990000735,-0.12819141948014,0.049719385451735,0.062387478969433,-0.051895939654627,0.062259345299517,0.10286840184125,-0.12062841491752,0.050091567269541,-0.10383957798859,-0.056606939630697,0.10252018272719,0.075507246935576,0.080158016013324,0.17676271442216,-0.13237776427722,0.030334410908607,0.053664701325162,0.019065130629655,-0.10861812739957,0.010342976250429,0.1455308649531,0.094345200983869,0.0071969743573567,-0.05569648366503,-0.024083938146062,-0.10268762385099,0.020854740874339,-0.032699151715468,-0.097303979991622,-0.12511863849588,0.028807022459574,-0.04107304254883,-0.16737260580647,-0.14200598699525,-0.096986889102051,-0.052562114438336,0.14115079510429,0.16913011070133,0.098837779634181,-0.087150242219434,0.036618272248255,0.068345542680719,-0.076292145588295,0.14905069546152,-0.11880700037392,0.15764905918189,0.066217195350131,-0.010651249420441,0.12295639560566,-0.15078079085278,0.061183805476738,0.00042846830146535,-0.14119001332795,0.020174486610046,0.062734169945711,0.059646729033622,0.047476053844389,0.093841455534999,-0.18497331912751,0.069013149510959,-0.074384653288464,-0.068483375575248,0.03473048352694,0.14801145182106,0.054636108471228,-0.18483532142893,-0.037622640899222,0.010187461664826,-0.19755056614867,-0.06485549570548,-0.029848369564663,-0.059618135850556,0.05034896449023,0.19227912544433,0.19819688851945,0.0027343826650071,0.06352065740319,0.034296903742036,0.036719424223823,0.052717571864766,0.053240140748183,0.015942955961298,0.032436888573437,0.092368907436766,0.030130669667024,0.043865401708296,-0.0068517649629237,0.010144462827127,0.17474063746576,0.24318012932029,-0.26786215083209,0.68169422594099,-0.19236539180865,-1.3116080444686,0.35420402607338,0.11921585396728,0.19323407494335,-0.21939610855853,0.42875750054723,-0.1205760178628,0.12949069574827,-0.26067794564722,-0.25369337535701,-0.78747927713512,-0.13802393090886,-0.52924367229459,1.1774529323071,0.21586284242234,-0.26398895268256,-0.072398174354151,-0.11784881466705,-0.2607089384219,-0.028897101787962,-0.10055788216947,-0.084980168302313,0.048580904149874,-0.086594341963661,0.12365699467176,0.44093203569579,-0.55739671701754,0.25736235030817,-0.036488236289771,-0.43792123925031,-0.4284164151316,-0.35116420814797,0.061385040203521,-0.14523809104676,-0.37514296685169,-0.14611363701141,0.51932107533015,0.10736618772824,-0.052877424351866,-0.21176852617183,-0.87228807429876,0.26708532070338,-0.066674998490496,-0.1114386052983,0.15574618531557,0.11854372496935,0.46914070856221,0.07990432300429,-0.077364566582721,-0.040216471016519,-0.11234155385513,-0.0039141592657082,-0.15265808623296,-0.13985585767209,-0.094287572716044,-0.24289202550711,0.0012239710027096,0.87981927301114,0.068878955539862,0.18308057211415,-0.076623213806279,-0.038690596642911,0.21166741650101,-0.089032728801981,-0.056301115829363,0.18311331881949,-0.13085140198571,0.021591541878985,-0.082749629541893,-0.2916990028592,0.28403218314849,-0.12824849146004,0.11144982038491,-0.21671700181668,-0.066550059241835,-0.11446306179478,0.052461554149467,-0.18181979114291,-0.058991091465289,-0.32954613860068,-0.85868246851699,-0.03662086510358,-1.7309768276003,0.30353549022131,0.69273947791784,-0.31468795218902,0.28573554515211,0.06219078774911,0.032873859902067,-0.21931469683759,-0.22282582640812,0.098699382073727,-0.062322371071258,-0.10479651982765,0.22334439575247,-0.094672718509831,-0.054306668865808,-0.30558349983785,-0.064061935173823,0.082246624988044,0.11693750696111,0.074696547258129,0.096849382544259,0.054450599378932,0.22250475091017,0.38757059440187,-0.52766535986325,0.17314486017203,-0.14578537788851,-0.33391567971114,-0.37326475347655,-0.27075707506557,0.10015581039769,0.15886087944271,0.024288426416362,0.23813549574885,0.08124840821622,0.51579492280235,0.052807187867913,-0.23262454085348,0.28468861393232,0.35600424876242,0.16821928276313,0.35727489984789,1.2516325996048,-0.32977934049028,0.19777931504453,0.18958945622276,0.75194493974401,1.2016756330106,0.18017051181092,-0.55727342914475,-0.47164655107065,-0.13675489842421,-0.13535652883925,-0.068694951569147,-0.076584425944564,-0.090571688467073,0.030508886579407,-0.25843023273111,-0.14092064538256,-0.083920166947276,0.06740276733689,-0.013747711703335,-0.16850646975342,0.20674133257788,0.018493582521505,-0.045951219036823,0.058692616895832,-0.10307066022316,-0.028992701798667,-0.096347272374428,-0.1749160136204,0.56872236378133,0.11152387173597,0.29601618534778,0.0052381796110448,0.10077794679103,0.1278862881389,-0.14485025858764,-0.16445643596067,-0.24864863041767,-0.10687158776391,0.14916686381965,0.12009553681304,0.032484279321654,-0.019903992714897,-0.6014070533719,0.024602641030587,-0.10944035286901,-0.0074629355948378,0.081839909453943,0.28071520007576,-0.16109671445054,-0.0070756945502701,-0.03646057281827,-0.057427647548336,0.29135211953042,0.20190337561519,0.062590396369546,0.092051600476933,-0.033240455513985,0.048773760294848,0.036923437396998,-0.14599636815696,-0.00082594914397388,0.24760011913352,0.15528397651089,-0.20581691812116,-0.19509956895829,0.041334234885368,-0.19972228303387,-0.048900774801976,0.18424526066572,-0.015058222231669,-0.12336252391956,0.23766630559129,-0.17565196123396,-0.0036641213771589,0.12368832019478,0.035557046973375,-0.090129205512828,-0.12548068385643,-0.077449490552464,0.031320655932032,-0.031628453968411,-0.080999019584015,-0.019711620594508,-0.14869631772085,0.035359001281439,0.0053724027665144,0.037646672573362,0.23445065560943,0.25296023237037,-0.15225224889603,0.086582237682362,0.010642867965957,-0.23680702218317,-0.065144182671406,-0.057664917850393,0.070222888380243,0.00043466800073326,-0.023946014418491,-0.13519045411793,0.024903136941893,0.13621608740994,-0.080771035744037,0.022832507184618,-0.060790492326462,-0.304786554049,-0.17959186308075,-0.047620907121611,-0.048919834663612,-0.10693569945403,0.0075653407092516,0.093813421764024,0.10225453886528,0.19966941889969,0.054429337765301,0.16855464674761,0.12467633022889,0.21578104809261,-0.010502116194329,0.14914488948095,-0.17051942295225,0.077843975812787,0.0069695963492174,-0.14668190046174,0.19421031672556,0.18801726057095,0.11217193492256,0.12144541116464,0.11374149726239,-0.33060544839377,0.11738013343487,0.2825846806343,-0.083708380274507,0.028547760722831,0.08340474528932,0.014765594125566,0.51162155008028,-0.089422612001682,-0.081097981172854,-0.10902261844413,-0.13227420062841,-0.092592238013944,-0.13206653560306,-0.1238338461133,0.12156555358234,-0.18861741436776,0.17475985412818,0.036474367575464,-0.031331716422507,-0.038495494297213,-0.17109915692745,-0.068298630453289,-0.18536677232194,-0.21416669810469,-0.13103194770892,-0.062948632535781,0.098283513465432,-0.74717279710586,-0.11095941507712,-1.0485851262894,-0.091318680889047,0.0052272540384209,-0.67733446608232,0.38240262518307,0.049571633716513,-0.7477411797569,-0.5397515823909,-0.03638139119322,0.026076242438123,-0.13861206701826,0.041342769311006,0.077588408124849,-0.039401233384243,0.14581617357463,-0.069916747813647,0.099381529813733,0.067310786537639,-0.15530178633934,-0.11529192500015,0.15008442687736,-0.020987263449963,-0.037706145532766,-0.066377046601323,-0.049561694915161,0.066199520967504,0.040364662795838,0.21397329804763,-0.064533027110964,0.059024977669959,0.063816949317062,0.019060529465654,-0.036801297350749,-0.035371782784707,0.030521363064731,-0.043755507385224,-0.021943755641858,-0.14338738946863,0.024856895200303,-0.12664276377149,-0.12710154143769,-0.14773851806844,-0.038130569746016,-0.18448160625121,0.059544215247055,0.02051661431833,0.02812239936899,-0.02190183929373,-0.045326415415478,0.054367300922556,0.028955225009773,-0.097035835003575,0.14649201641076,0.13010503116239,0.11220070295621,0.0360277623135,-0.11413956917666,-0.020288565698359,0.043018773964262,-0.055374734592633,-0.096812612883159,0.056503162016515,-0.13839233926956,0.053871113840598,0.23451189009684,-0.037017057258969,0.026687391376868,0.016131058920242,0.10520118669503,0.060230648104826,-0.098807253492042,0.076527791214278,0.11510064099546,0.10868911597861,-0.019728244535565,-0.14183685852879,0.14185713070128,-0.01594678722066,0.03285175797213,-0.024117018413218,-0.071928771689917,0.0039208676626186,-0.015320553340302,0.071412464583937,0.12896837324802,0.03295752893531,0.20250390898494,-0.060850592725247,0.028706422670559,0.13544883258512,-0.011018611854621,-0.02284618958877,0.14625428097931,0.18525658643465,0.0073351002634402,0.061231416402301,-0.13656924838089,0.069852459486405,-0.11330849426567,0.14004857214836,-0.027752211490644,0.095665817377664,0.13457760004885,0.084827618093125,-0.18673703959947,-0.028310015334208,0.0023949425868321,-0.085103683814703,-0.00031879800917564,0.12344064127376,-0.083087825378823,0.070410014850885,0.09291954807709,-0.041927445846002,-0.052821133552674,-0.13298315811927,0.02937081927646,-0.13082153209638,0.080820465348193,0.074821980888084,0.067026913092775,-0.12525746368194,0.1362454856537,0.096171777026381,0.10803987785754,0.044011358007849,0.10281037905082,-0.07158550166003,0.090797661068044,0.10016723324677,-0.04038930044283,0.02045073203869,-0.022721994351532,-0.059413244163342,0.12002701134074,0.061083245809624,0.15396012364713,-0.13119170167473,-0.058348061371104,0.15751561318308,0.020946345036308,0.0095624336476229,0.042574208617277,0.10612798087765,0.15773597796108,-0.0021478155692208,0.067436385023744,0.064249766045054,0.0012722680233097,0.0025187662769708,0.018707347260364,-0.050916491388613,0.042381080288218,-0.22296867276604,-0.088060218646091,-0.023735920609351,0.052937544307502,0.064302385231767,-0.038253969193581,6.2115780641511e-05,-0.018905411501198,-0.053943991483132,-0.077898972089079,0.036440997829226,-0.047523729113803,-0.054164373401951,0.062074619240234,0.2406000359559,-0.108617240915,0.029411760922862,-0.12354747997042,0.23818652907571,0.063163707507964,0.14722438249932,-0.031356909483795,-0.12209459736098,-0.024760132505966,-0.031759953807373,0.093188003025443,-3.0865800008976e-05,0.016519601596559,0.11804874132783,-0.0034992326595574,0.029061472911434,0.23465153264343,0.060691539083971,-0.11908633598443,0.10265353365948,0.12885901592365,0.019931187707258,0.14022928400391,-0.12744872681248,0.10062951594598,-0.16157162794688,0.039668330635405,-0.059484624845155,-0.0083852081364065,0.077763486079811,-0.10002863954823,0.060779683336361,0.12027656539773,-0.19788658750278,-0.18673151779234,-0.0045767655252258,-0.093216766792578,0.10030455108731,0.28456122901983,0.12170333814228,-0.096561853656555,0.041271637085671,-0.12499781428027,-0.060927252991319,-0.0094519140728149,-0.31823140048446,0.0307162501179,0.16858638867284,-0.0051450977084743,-0.5596093024092,-0.049363559707029,0.014630605463076,-0.13936032528551,-0.052996703625787,-0.00099637697921325,0.016160749966345,-0.038853734709322,-0.43161481960859,0.14043063561622,-0.023247342449782,-0.18173498827307,-0.071974778028093,-0.066854011247439,0.14551895704023,-0.029462577141583,-0.02348928111994,-0.29065162446183,0.089018856645277,0.10528306635199,-0.18506495370532,0.07458842840567,0.079188679059997,-0.0203396939238,-0.016364670482183,0.023959442123639,0.066535556676005,-0.24779035034448,-0.29673466289592,0.12348099433579,-0.013230872893804,0.06617781802032,0.14774936072822,-0.070646793221979,0.13254435295433,0.049982607087863,-0.04776040486988,-0.050485388990429,-0.053700306796498,0.12088575129222,0.16077964460525,-0.055581916780996,-0.0057870954291331,0.13832787757677,0.06222188129765,0.10759558927771,-0.13039905220709,0.031807764792737,-0.072892053271904,-0.075469762263388,-0.15014283806051,-0.15412440247801,0.077815778172336,-0.047294907931671,-0.025563275628335,0.069203175777593,-0.12629073364015,-0.1631172788939,0.012762108780592,-0.23701156485063,0.03193119309948,-0.44609787627419,-0.11876957066304,0.070401188236751,0.063990933939996,-0.40346195616801,0.15738017512105,0.82314350335,-0.87729943942059,1.7028499770364,-0.75642803780105,-0.97162354736729,0.42141566333742,0.53582835151938,0.081550804124923,-0.058643881180283,0.41779710662657,0.12648750004568,-0.003157967973938,-0.053427049947482,-0.10619069665993,-0.072627265959847,0.028889835483057,0.59575395104498,0.016548608900014,0.15429837635658,0.17464428883692,0.059045098694615,1.1106725616807,0.19651337259404,0.85738535813761,0.77307577213979,0.78951966651255,0.075630127664955,0.1360760814827,-0.053335290819218,-0.21391394944999,0.18834561384434,-0.043245612639547,2.9364017619229,0.3139241155213,0.5505384029169,0.72000979913479,-0.7974170164063,0.16452400700676,-0.92655723138087,0.11561960227861,-0.13483776037403,-0.096746276193107,0.085262461962407,-0.075767377533392,-0.1218626411094,0.029084912863608,0.14043385201599,0.16202731799511,0.058783474233539,0.20176332229516,0.17191158791727,0.14662119653305,-0.039532873677959,0.0012365004353692,0.053936148369788,0.0057653973632623,-0.10418740013363,0.027738105431465,-0.069805593145171,0.10267871957104,-0.25405622200964,0.34322717941103,0.087489713561881,0.21868815735753,0.10576826730645,-0.14068329266668,0.047513010686348,0.29518977674653,-0.14950765937894,0.12876085507528,-0.048298411804911,-0.377330539262,-0.068150133860231,-0.001611480325189,-0.20029161401044,-0.010395262964137,-0.16173657716662,0.11948917006682,0.088279096188993,-0.11416444815987,0.133099304224,0.057643942020466,0.17930310156188,-0.052667101891772,-0.16004284678074,0.18900769730443,0.007930032816283,0.00023647180750157,0.10813196509635,-0.12010487701399,0.18692291269905,0.11748653492354,0.0780550407838,-0.0083814299468757,-0.10572858535467,0.039438115674588,0.018562136820077,0.10625439952288,0.048123796138742,-0.015076021261846,0.024687314540868,0.22950276914388,0.08111945782385,-0.10592559086487,0.14704069059932,-0.059297646324001,-0.029957879671374,-0.03575927915359,-0.022416855641893,0.14026188348938,0.057812390805214,-0.11509977423769,0.092011866679456,0.017590386952999,-0.037813845818014,0.10367522822608,0.16281872420124,-0.066399665241379,0.016600543237443,0.21774718760355,-0.0056209982192873,0.069418383660136,0.14783026204419,0.020586788623959,0.18384435694815,0.075632126170571,0.0016361031616262,-0.00063855096425734,-0.043507636597844,-0.060731985888095,-0.13665137982828,0.11560298732107,-0.152950979113,0.060045401662319,-0.02642212351164,-0.081791176586504,0.05219195352836,0.031625594053015,-0.082998488267733,0.0064816630272097,-0.011179320259706,0.1408454205024,-0.048120137036807,-0.16134321448753,-0.085910799395906,-0.092205546200344,-0.054973010377873,-0.084698215785963,-0.16707127547097,0.055037304268422,0.022415649178604,-0.079106191968881,-0.016709607057057,0.072561005280842,0.15791833372862,0.095157102053929,0.044958397419941,-0.037766742319493,-0.026020106345806,0.0084748915596655,-0.17101494001648,-0.33552111762895,0.15202742396554,0.25568367401401,-0.19672917106306,-0.14689616107265,0.059628932736276,-0.13891873342014,-0.10504577509623,-0.036499097933258,-0.13500457227867,-0.076307906110503,0.075919420158928,0.015075415249832,-0.033950884412959,0.15962736207519,0.15930953094381,0.14739376298228,-0.19474416559922,-0.41205126035229,0.1152117910631,-0.010523050766837,0.19205058682717,-0.10999101920923,0.13309240602636,-0.18604449430117,-0.17573135242437,-0.30650848725545,-0.0014101470252689,0.13026369752575,0.18433357588401,-0.15787879447927,0.22582378175881,0.046816373276256,-0.030957824596946,-0.26571949217161,0.22548023058297,-0.0095361276601986,0.089774429748915,-0.22347963525729,0.093089905714993,0.029347625502884,-0.2025899086647,0.013879943579676,0.17814115124968,0.38862447596947,-0.05850761788163,0.10374244048482,0.0047651355983452,0.049449664412895,0.0073047473818296,-0.19273055544575,-0.14133194298112,0.21355587092644,-0.64459100326495,-0.58043881813175,-0.44980519560764,-0.35213440960481,0.75273310724602,0.38654837708538,-0.25200927388551,1.0734910875511,-0.16716411911702,0.19394826035614,0.25239557544746,0.37825123096156,0.015014497120322,-0.60349132850596,-0.17986526430567,-0.042421581931521,-0.26555076379334,0.91215406535564,0.13528424395775,0.25992998757556,-0.27026348567523,0.043330835344226,0.19261498098496,0.20312697410649,0.056325216837184,0.15726483769767,0.1823498665792,0.059749758544511,0.087750961013662,0.12227700592391,-0.16863390340479,-0.10171398233013,-0.013817165505885,0.37345304987297,0.20796011434997,-0.034561472922187,-0.0043175458271674,0.087480314831105,0.029893192267464,-0.17997602635457,0.27082477811736,0.20889969808091,-0.095541541148754,-0.0057487823424413,-0.12790106932745,0.019000864610486,0.19868075490164,-0.30387991412496,-0.10407114780602,0.1761151569595,-0.33251259790463,0.20901039398156,-0.037324138284972,0.227591478055,-0.011985169121957,-0.15271517690228,-0.14581060954931,0.1529328501013,0.10098950688029,0.064659202545259,0.19037100366545,0.49716747416699,0.00079846226711921,0.057003143626769,-0.067506328747799,-0.074007041828111,0.47040549504595,-0.084063154381955,-0.10020393943328,0.064088041708141,-0.043581935033315,-0.045007028979958,0.13620629994414,0.056067588234928,0.15961459506052,0.019875600861268,-0.1582782922953,0.16792929599851,0.15948008500646,-0.022428432568326,0.10435524142814,0.15506013516575,-0.20859195956242,-0.19494490901556,-0.11733785243581,-0.025456939768586,-0.52915044518732,-0.090570334065597,-0.17957600918654,-0.37601141347052,-0.044465291289835,-0.19908107383923,0.25565365326705,-0.3886734043745,-0.12732938360489,0.043665874056041,0.15846976835206,-0.089359531442571,0.27935007750665,0.11715111692439,-0.047086351461072,-0.21754561242935,-0.20411518919154,-0.092355127818225,0.015405407750322,0.11830250898144,-0.085229573723706,0.017890230860171,0.059952504223756,-0.1840199476433,-0.22774083246845,0.047349972384693,0.16086572981032,-0.075054001296643,-0.032930317717539,-0.085016324596106,-0.090150281561545,0.18934301507883,0.13638945473891,0.022195309761737,-0.09752857350239,0.15311234831453,-0.092851247748138,-0.49203082419429,-0.23764538530791,-2.1097689306153e-05,0.1032107169775,-0.23750808888447,0.016913634024218,-0.005703203440889,0.51687203437679,0.10709645287878,-0.2386599332432,-0.36838766240689,-0.23758082031027,-0.043817072252978,-0.1309367835136,-0.35901089956478,0.090064336753958,0.028080448942506,-0.077295483540038,-0.035400089946365,0.10500809437259,-0.069942498286855,-0.17201493802325,0.15757917690287,0.079463638146939,-0.12148762709719,0.12554495088687,-0.16810389479484,0.022804772898827,-0.025138636594947,0.056419498352752,0.0065560843337618,0.13544595057752,-0.0041936074081708,-0.0020064466705303,0.74292088365016,-0.19188235002303,-0.36483713712732,0.02436647814041,-0.14570553500493,0.27997944009825,-0.026676685001691,0.38560932782181,-0.12977946897074,-0.17637582313037,0.16034508580051,0.18132650097521,-0.15929710897117,-0.15472804857985,0.63307152126401,0.11795048292441,0.0075545057887054,0.37597522728155,-0.15680347032942,0.023136340522057,0.035194681174661,-0.048820534327916,-0.11605926134535,0.25614218325216,0.14794872637432,-0.042655447203179,-0.13919114396412,0.077014978368279,-0.0642085346228,0.056921243583505,0.093391341660546,0.048620332043952,-0.12147209618098,0.23765365440042,-0.059843063032931,-0.26252505039506,-0.19285606194181,-0.058469051860594,-0.0070155937151498,0.0060632676814378,-0.063192463241814,0.11252996159446,0.064977714449768,-0.11314075949904,0.13979832289602,0.16148034490591,-0.21101669733565,-0.19761061212767,-0.04620410823348,0.16182590479527,-0.56496749960133,0.12719297358802,0.032524885756025,-0.022847523482375,-0.077457097302322,0.094352758199453,0.044438473727453,0.1713941773404,-0.11549669608389,0.18653868994909,0.12125703537405,-0.11458611184535,-0.0020829893111009,0.16223837740258,-0.12184587526488,0.17734060392402,-0.015244065833992,-0.0065818901738635,-0.04294832182402,-0.27244648054922,0.081268701839698,-0.17953708485256,0.0099587858874865,0.044449934956204,-0.034684098620732,-0.012039142215473,-0.22117034351173,-0.3758277492615,0.044936174505007,0.031102373505916,0.042722022050983,-0.038821469745007,-0.14025750214074,0.044647326292503,-0.063495500112896,0.018696934646252,0.18644812416545,-0.012343687316131,0.043828680251609,0.0926995413765,0.095753710493926,-0.012862752880606,-0.3350147772593,0.17363817381072,-0.21866503644875,-0.20352048689251,-0.22885382679272,0.034409510702691,-0.17843414110698,-0.085199033772984,0.57568863637709,-0.031922659959492,0.31254703854676,0.11976001010443,-0.0098148813566248,0.080565049456708,0.19133929218899,-0.029988474712791,0.094238171272157,0.44909524965109,0.028318316101423,-0.37157581521044,0.13364086335859,0.20977070655124,0.24980745476806,0.091162030407174,0.40980947806575,-0.057489914849861,0.098967475046331,-0.28154004221255,-0.024780992747671,0.28299713063254,0.075708798253214,0.17186039838091,0.50134153644647,0.33779641795996,0.018748267465454,-0.061223971146696,0.59327671640933,0.61028276282723,-0.87302172107169,-0.027602708716036,0.6784523038868,0.53266674948013,0.24251240162914,0.1764300357937,0.034165937628821,0.16761208512538,-0.014937529749975,0.0085546831367286,-0.070490891676238,0.04505968426676,-0.080380514600603,-0.11823551045879,0.084559979193852,-0.012423444152318,-0.18410323967708,0.083896004373538,-0.073110309524894,0.087980982240723,-0.037976111596736,-0.00066356407455854,0.034319725169755,0.052487623291985,-0.12269132608571,-0.086212117317011,-0.094146030750369,-0.45468082733982,-0.11262819171184,-0.19166475004216,-0.49096532466723,0.4069282344275,0.080659886910744,0.29300375542687,-0.19386424347878,-0.053742980700324,0.084757225952031,-0.056881716621373,0.049204142464974,-0.018375299902164,0.26190744518424,-0.38666850946403,0.10055813052139,0.071801379024157,0.23061138211459,0.16690409837979,0.26553670456689,0.26003037175793,0.13891333884357,0.0016103120019376,0.16105180773314,0.12183569879764,-0.24970721854452,0.0033252135809914,0.0069043626020825,0.1534128061482,-0.052940401993913,-0.14457015357523,-0.27545984959895,-0.088962265399963,-0.27990395550809,-0.15058208962411,-0.082399752400822,0.036994199729249,0.14251218501097,-0.26431529414537,0.12477907521882,0.1548851159374,0.17849014313696,-0.033687076456719,0.17837667755773,0.035532514243317,0.0055064757196971,-0.15340606903214,0.0013370663066159,0.15957370734162,0.12794089985965,0.27857937672751,-0.005203542508125,-0.043397288152701,-0.17171938637924,0.048311651982051,0.00086626839528513,0.034357164119278,0.032791692791059,-0.0019883621944776,-0.24739707615346,0.072108605336939,0.21015209761306,-0.2860971714061,0.081441156318284,-0.071245497624116,-0.095300169300122,0.15725948885212,-0.016384486277619,0.063608918483068,0.23749404921341,0.088301063085846,0.034496877874929,-0.21559780185518,0.060659177216816,0.016302503162917,0.20679219170879,-0.016362053926675,0.18979129089682,0.23721734396363,-0.097671897485288,0.24660335807373,-0.068412265832006,-0.19710795154877,-0.012231285544392,-0.57539949338072,0.0062636348000125,-0.43875761064729,-0.067884654271786,-0.023071826181826,-0.096882030767835,0.08573611527422,0.23485000641518,0.090335244181311,-0.036607700005836,0.12759704924369,0.14826454372134,0.054513715877748,0.21143619708791,0.15527646211111,0.098129069070491,0.4095815281177,-0.018442295432053,-0.24355689170092,0.1202135335337,-0.064801440304258,0.018294206967245,-0.093273800380567,-0.25437109654974,-0.1747147386549,-0.36971438240118,0.30118761856682,-0.19022019410588,-0.060475361920101,0.012154000972083,-0.098222643275471,-0.035916378647046,0.14361942213574,0.17581502816133,0.19327425161411,-0.28610705637265,0.1899814271259,0.42690840714857,0.39790617339999,-0.29136657151724,0.15285684110437,-0.0082476456578457,-0.23778072621363,0.20241811596315,-0.091012998724936,-0.14795237525428,-0.15548403636992,-0.32647661796122,-0.30735849294282,-0.11368422655348,0.050939130164472,-0.37238457704918,0.00073417606620696,-0.22739271286354,-0.38738144924922,-0.13480381721645,-0.023912500635388,0.044932632170509,0.1742384110806,-0.050953135201172,-0.070855351036204,0.046041355663835,0.23903390737507,0.050365770909827,0.011271786886836,0.16721165555744,-0.02366353118708,0.029486776323106,-0.16244108474221,-0.079365348830297,0.10368503177414,0.072235458934008,-0.028292560825243,0.78815931950632,-0.36415240893376,-0.3070213936683,0.084527785504097,-0.8499777569803,-0.30550511820584,0.062128263071728,-1.4215173487816,-0.50894992877069,-0.010300683665399,-1.5328868935464,0.41918149144797,-0.88353681813946,-0.50190354902837,-0.78133681998031]}